<?xml version="1.0" encoding="UTF-8"?>
<tv generator-info-name="WebGrab+Plus/w MDB &amp; REX Postprocess -- version  V3.3.0.0 -- Jan van Straaten" generator-info-url="http://www.webgrabplus.com">
  <channel id="フジテレビ">
    <display-name lang="ja">fujitv.jp</display-name>
    <url>http://www.tvguide.myjcom.jp</url>
  </channel>
  <programme start="20230311001000 +0000" stop="20230311005500 +0000" channel="フジテレビ">
    <title lang="ja">FNN　Live　News　α【WBCダルビッシュ先発▽福島に脱炭素型工場を】[字]</title>
    <desc lang="ja">福島に脱炭素型工場を水素で見据えるミライ▽WBC侍×韓国詳報4勝4敗…宿敵と対戦.(n)</desc>
  </programme>
  <programme start="20230311005500 +0000" stop="20230311012500 +0000" channel="フジテレビ">
    <title lang="ja">連続ドキュメンタリー　RIDE　ON　TIME&lt;フジバラナイト　FRI&gt;</title>
    <desc lang="ja">エンターテインメントのバックステージを放送する連続ドキュメンタリー番組。ある1つのテーマを長期密着取材し、複数週に渡ってリアルを描き出します。.(n)</desc>
  </programme>
  <programme start="20230311012500 +0000" stop="20230311015500 +0000" channel="フジテレビ">
    <title lang="ja">マイクロコントラボ〜セレクション&amp;製作秘話〜&lt;フジバラナイト　FRI&gt;</title>
    <desc lang="ja">大好評!人気芸人EXIT×マヂラブ×かが屋「EXITV」発のコント特別番組▽発想豊かなコントキャラが生まれた(秘)打ち合わせ風景公開▽話題の完全版チラ見せ.(n)</desc>
  </programme>
  <programme start="20230311015500 +0000" stop="20230311025500 +0000" channel="フジテレビ">
    <title lang="ja">CoA〜Highlights〜&lt;フジバラナイト　FRI&gt;【CoAダイジェスト!】</title>
    <desc lang="ja">CoAでこれまでに完成した作品創作を一挙放送!▽気鋭の現代アーティストの創作活動を通じてアートを身近に感じる、MC無し専門家解説無しの新感覚アート番組.(n)</desc>
  </programme>
  <programme start="20230311025500 +0000" stop="20230311032500 +0000" channel="フジテレビ">
    <title lang="ja">CSちゃん&lt;フジバラナイト　FRI&gt;【SUPER　JUNIOR生中継直前SP】</title>
    <desc lang="ja">フジテレビCS放送のイチオシ番組を紹介。今回は2022年に行われたSUPER　JUNIORの2年ぶりの来日イベントの模様をダイジェストでOA。.(n)</desc>
  </programme>
  <programme start="20230311032500 +0000" stop="20230311042500 +0000" channel="フジテレビ">
    <title lang="ja">自由な女神-バックステージ・イン・ニューヨーク-&lt;フジバラナイト　F…　#01[再]</title>
    <desc lang="ja">ドラァグクイーン(武田真治)(秘)ショーを観ると人生が変わる!!空気読みすぎのさえない女子(井桁弘恵)の運命は…ファッションあり三角関係ありちょっとディープな上京物語.(n)</desc>
  </programme>
  <programme start="20230311042500 +0000" stop="20230311044000 +0000" channel="フジテレビ">
    <title lang="ja">ディノスTHEストア</title>
    <desc lang="ja">通販のディノスが自信を持ってお届けする「今がカイドキ!」な商品をご紹介!ゲストの皆さんの本音のリアクションも交えて、商品の魅力を解説します!(n)</desc>
  </programme>
  <programme start="20230311044000 +0000" stop="20230311045000 +0000" channel="フジテレビ">
    <title lang="ja">ディノスTHEストア</title>
    <desc lang="ja">通販のディノスが自信を持ってお届けする「今がカイドキ!」な商品をご紹介!ゲストの皆さんの本音のリアクションも交えて、商品の魅力を解説します!(n)</desc>
  </programme>
  <programme start="20230311045000 +0000" stop="20230311045200 +0000" channel="フジテレビ">
    <title lang="ja">SOUND　WEATHER</title>
    <desc lang="ja">メジャー、インディーズを問わず、良質なポップミュージックのプロモーションビデオにのせて、翌日のお天気をお届けする音楽プログラム。.(n)</desc>
  </programme>
  <programme start="20230311045200 +0000" stop="20230311052200 +0000" channel="フジテレビ">
    <title lang="ja">テレビ寺子屋【テナガザルの親子の絆/小菅正夫】</title>
    <desc lang="ja">「テナガザルの親子の絆」\n小菅正夫(札幌市円山動物園参与).(n)</desc>
  </programme>
  <programme start="20230311052200 +0000" stop="20230311053000 +0000" channel="フジテレビ">
    <title lang="ja">ぼのぼの[字]</title>
    <desc lang="ja">「友達は古くなる?」\n登場キャラクター:ぼのぼの　シマリスくん　アライグマくん　ぼのぼののおとうさん　コヒルマン　他.(n)</desc>
  </programme>
  <programme start="20230311053000 +0000" stop="20230311060000 +0000" channel="フジテレビ">
    <title lang="ja">週刊フジテレビ批評</title>
    <desc lang="ja">東日本大震災から12年〜20歳の若者たちの選択〜笠井アナが被災地南三陸を取材。生まれ育った街に残るのか?離れるのか?それぞれの葛藤と決断に迫ります。.(n)</desc>
  </programme>
  <programme start="20230311060000 +0000" stop="20230311083000 +0000" channel="フジテレビ">
    <title lang="ja">めざましどようび[デ]</title>
    <desc lang="ja">侍Jが運命の韓国戦!ファン&amp;列島が大興奮▽学校で異臭生徒搬送▽羽生結弦が被災地でアイスショー▽綾瀬はるかのご褒美▽B'zがサプライズ▽目黒蓮メンバーを思い涙.(n)</desc>
  </programme>
  <programme start="20230311083000 +0000" stop="20230311095500 +0000" channel="フジテレビ">
    <title lang="ja">土曜はナニする!?【★最新!無印良品SP★激ウマ100円おかず★富士の絶景旅】[字]</title>
    <desc lang="ja">山里亮太&amp;宇賀なつみがアナタの週末を楽しくするお手伝い!(n)</desc>
  </programme>
  <programme start="20230311095500 +0000" stop="20230311102500 +0000" channel="フジテレビ">
    <title lang="ja">サスティな!【驚きのセカンドライフを過ごすデジタルシニアの素顔に迫る!】[字][解]</title>
    <desc lang="ja">国際女性デー特集第2弾!驚きのセカンドライフに密着!世界中のIT企業が熱視線を送る世界最高齢〇〇&amp;登録者数急上昇中!一風変わったVTuberの秘密とは.(n)</desc>
  </programme>
  <programme start="20230311102500 +0000" stop="20230311110500 +0000" channel="フジテレビ">
    <title lang="ja">いただきハイジャンプ【シーパラでクイズバトル!ジャンポケ斉藤の期待に山田が…】[字]</title>
    <desc lang="ja">山田&amp;ジャンポケ斉藤VS高木&amp;八乙女でクイズバトルin八景島シーパラダイス!山田が“海のライオン"とコラボ!しかし斉藤が…高木&amp;八乙女奇跡をおこす!?(n)</desc>
  </programme>
  <programme start="20230311110500 +0000" stop="20230311115000 +0000" channel="フジテレビ">
    <title lang="ja">KinKi　Kidsのブンブブーン【勝地涼のわがまま秋葉原ツアー】[字]</title>
    <desc lang="ja">昨年12月オープン概念が変わる絶品塩つけ麺に感動▽大人気忍者喫茶でニンニン大はしゃぎ!?▽キンキが勝地を全身花柄コーディネート▽親友から(秘)タレコミ情報.(n)</desc>
  </programme>
  <programme start="20230311115000 +0000" stop="20230311120000 +0000" channel="フジテレビ">
    <title lang="ja">FNN　Live　News　days[字]</title>
    <desc lang="ja">週末の昼も「ライブニュース　デイズ」をお見逃しなく。民放で最大級の全国ネットワークを持つFNNの記者が取材したニュースをお届けします。.(n)</desc>
  </programme>
  <programme start="20230311120000 +0000" stop="20230311133000 +0000" channel="フジテレビ">
    <title lang="ja">ぶらサタ・タカトシ温水の路線バスで!【レトロバス「あかいくつ」で楽しむ横浜】[字]</title>
    <desc lang="ja">「今回はレトロバスあかいくつで楽しむ横浜!中華街で顔より大きい唐揚げに驚き、番長デカ盛りねぎとろ丼に感動!路地裏の名店で出会った究極のまかない飯とは」.(n)</desc>
  </programme>
  <programme start="20230311133000 +0000" stop="20230311143000 +0000" channel="フジテレビ">
    <title lang="ja">土曜RISE!・我流しか勝たん!〜生活革命新裏技〜【絶品!卵料理&amp;ハンバーグ】[字]</title>
    <desc lang="ja">卵焼き・卵サンド・卵とじ…お手軽アレンジで大変身!絶品卵料理が続々登場▽秒殺!ゆで卵の殻の早むき方法▽プロが教える!簡単マネできる肉汁たっぷりハンバーグの作り方.(n)</desc>
  </programme>
  <programme start="20230311143000 +0000" stop="20230311155500 +0000" channel="フジテレビ">
    <title lang="ja">わ・す・れ・な・い　映像教訓　巨大地震から生き延びる[字]</title>
    <desc lang="ja">福島「中通り」震度6強の脅威…犠牲者8人ダム決壊その時何が▽映像検証…都市での避難どうする?横浜の事例▽関東大震災100年…112歳の生き証人語る教訓.(n)</desc>
  </programme>
  <programme start="20230311155500 +0000" stop="20230311160000 +0000" channel="フジテレビ">
    <title lang="ja">ガイド</title>
  </programme>
  <programme start="20230311160000 +0000" stop="20230311162500 +0000" channel="フジテレビ">
    <title lang="ja">社長の晩酌[字]</title>
    <desc lang="ja">いま話題の企業の社長が人知れず訪れるBAR。居合わせる常連客の藤木直人が、躍進企業の社長のヒミツを、シャープな質問で次々に明かしていくトーク番組です。.(n)</desc>
  </programme>
  <programme start="20230311162500 +0000" stop="20230311163000 +0000" channel="フジテレビ">
    <title lang="ja">フジナビ!</title>
    <desc lang="ja">フジテレビのおすすめ番組をこっそり視聴者のあなたにナビゲート。\n見逃せない番組の見どころを紹介しちゃいます!(n)</desc>
  </programme>
  <programme start="20230311163000 +0000" stop="20230311172500 +0000" channel="フジテレビ">
    <title lang="ja">来週金曜よる8時は「赤い霊柩車FINAL」放送直前!30年の歩みSP[字]</title>
    <desc lang="ja">「赤い霊柩車」シリーズ最終作を前に、片平なぎさ、山村紅葉に特別インタビュー!知られざるエピソードや今作の魅力をお届けします!(n)</desc>
  </programme>
  <programme start="20230311172500 +0000" stop="20230311173000 +0000" channel="フジテレビ">
    <title lang="ja">ガイド</title>
  </programme>
  <programme start="20230311173000 +0000" stop="20230311180000 +0000" channel="フジテレビ">
    <title lang="ja">FNN　Live　News　イット![字]</title>
    <desc lang="ja">▼東日本大震災から12年亡き人へ鎮魂の祈り▼被災地はいま・岩手陸前高田・宮城石巻・福島富岡から中継▼岸田首相が福島へ▼WBC佐々木朗希が今夜登板▼王将戦第6局▼.(n)</desc>
  </programme>
  <programme start="20230311180000 +0000" stop="20230311183000 +0000" channel="フジテレビ">
    <title lang="ja">MUSIC　FAIR【エレファントカシマシ・CHEMISTRY・森山直太朗】[字][解]</title>
    <desc lang="ja">35周年エレカシ!直太朗とSPコラボ「月夜の散歩〜今宵の月のように」ケミストリー大ヒット曲「My　Gift　to　You」直太朗「さもありなん」エレカシ新曲も.(n)</desc>
  </programme>
  <programme start="20230311183000 +0000" stop="20230311190000 +0000" channel="フジテレビ">
    <title lang="ja">イタズラジャーニー【かまいたちチョコプラの過激旅】[字]</title>
    <desc lang="ja">ウィンタージャーニー開幕!群馬のゲレンデで次々と襲いかかるイタズラ…松尾不在でフジモンが緊急助っ人!雪山で超至近距離ドッジボール&amp;イタズラソリ対決.(n)</desc>
  </programme>
  <programme start="20230311190000 +0000" stop="20230311210000 +0000" channel="フジテレビ">
    <title lang="ja">芸能人が本気で考えた!ドッキリGP　スノーマン爆破!目黒蓮が本気出すSP[字]</title>
    <desc lang="ja">SnowMan目黒・渡辺・深澤・宮舘がボムマジ爆発緊急参戦▼このドッキリがすごかった2023大賞が決定!菊池風磨の全裸大名・向井康二が考えたドレミのうた.(n)</desc>
  </programme>
  <programme start="20230311210000 +0000" stop="20230311232000 +0000" channel="フジテレビ">
    <title lang="ja">土曜プレミアム・映画「HERO」【伝説ドラマの映画版第2弾!】[字][解][デ]</title>
    <desc lang="ja">木村拓哉・北川景子、そして松たか子扮する雨宮も登場!大使館前で起きた不可解な事故…乗り越えられない“壁"を前に型破りな検事・久利生が真実を追い求める!(n)</desc>
  </programme>
  <programme start="20230311232000 +0000" stop="20230311235000 +0000" channel="フジテレビ">
    <title lang="ja">さんまのお笑い向上委員会【M-1準優勝の本格派漫才師さや香VSギャル芸人軍団】[字]</title>
    <desc lang="ja">M-1準優勝の本格派漫才師さや香がギャル芸人から強烈クレーム!前R-1準優勝ZAZYこじらせ中!ノブコブ吉村金で買ったギャグ!盟友笑福亭笑瓶をしのぶ会.(n)</desc>
  </programme>
  <programme start="20230311235000 +0000" stop="20230312004500 +0000" channel="フジテレビ">
    <title lang="ja">&lt;土ドラ&gt;自由な女神【(秘)ショー話題騒然!クセがすごいZ世代に悶絶!?】　#02[字]</title>
    <desc lang="ja">デザイナーになるべく上京したサチ(井桁弘恵)をめぐる三角関係に早くも急展開が!!大ヒット曲「迷い道」を使ったミント(武田真治)のショーは誰の人生をどう変えるのか?(n)</desc>
  </programme>
  <programme start="20230312004500 +0000" stop="20230312012500 +0000" channel="フジテレビ">
    <title lang="ja">S-PARK【快調侍ジャパン選手の声たっぷり&amp;レジェンド注目のサキドリランナー】</title>
    <desc lang="ja">S-PARKスポーツ・パーク佐久間みなみ\n▼WBC14年ぶりの世界一へ3.11決戦\n▼レジェンドランナーも一押しパリ五輪候補\n▼卓球世界最高峰ツアーが幕開け.(n)</desc>
  </programme>
  <programme start="20230312012500 +0000" stop="20230312015500 +0000" channel="フジテレビ">
    <title lang="ja">馬好王国〜UmazuKingdom〜</title>
    <desc lang="ja">競馬関係者100人が選ぶ「福永祐一ベストパートナー」を当てる5連単クイズ▼無敗の3冠馬や悲願のダービー制覇の名馬も登場▼完全的中へ豪華メンバーが集結!(n)</desc>
  </programme>
  <programme start="20230312015500 +0000" stop="20230312025500 +0000" channel="フジテレビ">
    <title lang="ja">女神の教室〜リーガル青春白書〜&lt;フジバラナイト　SAT&gt;　#09[再][字][解]</title>
    <desc lang="ja">[ついに最終章!!]藍井VS風見!判決に不服を持つ風見が無罪判決を執拗に追う理由とは!?そして、予期せぬ結末へ!!(n)</desc>
  </programme>
  <programme start="20230312025500 +0000" stop="20230312043500 +0000" channel="フジテレビ">
    <title lang="ja">世界スピードスケート選手権2023&lt;フジバラナイト　SAT&gt;</title>
    <desc lang="ja">スピードスケート世界頂上決戦!日本の女王・高木美帆&amp;五輪メダリスト佐藤綾乃&amp;次世代ヒロイン堀川桃香!男子は新濱立也&amp;村上右磨&amp;森重航の短距離勢に注目!(n)</desc>
  </programme>
  <programme start="20230312043500 +0000" stop="20230312235000 +0000" channel="フジテレビ">
    <title lang="ja">ミミヨリ!</title>
    <desc lang="ja">耳より情報をお届けします!(n)</desc>
  </programme>
  <programme start="20230312235000 +0000" stop="20230313004500 +0000" channel="フジテレビ">
    <title lang="ja">&lt;土ドラ&gt;自由な女神【(秘)ショー話題騒然!クセがすごいZ世代に悶絶!?】　#02[字]</title>
    <desc lang="ja">デザイナーになるべく上京したサチ(井桁弘恵)をめぐる三角関係に早くも急展開が!!大ヒット曲「迷い道」を使ったミント(武田真治)のショーは誰の人生をどう変えるのか?(n)</desc>
  </programme>
  <programme start="20230313004500 +0000" stop="20230313012500 +0000" channel="フジテレビ">
    <title lang="ja">S-PARK【快調侍ジャパン選手の声たっぷり&amp;レジェンド注目のサキドリランナー】</title>
    <desc lang="ja">S-PARKスポーツ・パーク佐久間みなみ\n▼WBC14年ぶりの世界一へ3.11決戦\n▼レジェンドランナーも一押しパリ五輪候補\n▼卓球世界最高峰ツアーが幕開け.(n)</desc>
  </programme>
  <programme start="20230313012500 +0000" stop="20230313015500 +0000" channel="フジテレビ">
    <title lang="ja">馬好王国〜UmazuKingdom〜</title>
    <desc lang="ja">競馬関係者100人が選ぶ「福永祐一ベストパートナー」を当てる5連単クイズ▼無敗の3冠馬や悲願のダービー制覇の名馬も登場▼完全的中へ豪華メンバーが集結!(n)</desc>
  </programme>
  <programme start="20230313015500 +0000" stop="20230313025500 +0000" channel="フジテレビ">
    <title lang="ja">女神の教室〜リーガル青春白書〜&lt;フジバラナイト　SAT&gt;　#09[再][字][解]</title>
    <desc lang="ja">[ついに最終章!!]藍井VS風見!判決に不服を持つ風見が無罪判決を執拗に追う理由とは!?そして、予期せぬ結末へ!!(n)</desc>
  </programme>
  <programme start="20230313025500 +0000" stop="20230313043500 +0000" channel="フジテレビ">
    <title lang="ja">世界スピードスケート選手権2023&lt;フジバラナイト　SAT&gt;</title>
    <desc lang="ja">スピードスケート世界頂上決戦!日本の女王・高木美帆&amp;五輪メダリスト佐藤綾乃&amp;次世代ヒロイン堀川桃香!男子は新濱立也&amp;村上右磨&amp;森重航の短距離勢に注目!(n)</desc>
  </programme>
  <programme start="20230313043500 +0000" stop="20230313050500 +0000" channel="フジテレビ">
    <title lang="ja">ミミヨリ!</title>
    <desc lang="ja">耳より情報をお届けします!(n)</desc>
  </programme>
  <programme start="20230313050500 +0000" stop="20230313051000 +0000" channel="フジテレビ">
    <title lang="ja">SOUND　WEATHER</title>
    <desc lang="ja">メジャー、インディーズを問わず、良質なポップミュージックのプロモーションビデオにのせて、翌日のお天気をお届けする音楽プログラム。.(n)</desc>
  </programme>
  <programme start="20230313051000 +0000" stop="20230313054000 +0000" channel="フジテレビ">
    <title lang="ja">キャラダチミュージアム〜MoCA〜【キャラが集まる不思議な美術館】</title>
    <desc lang="ja">キュレーター和田彩花がお届けする大人も子供も楽しめるPOPな情操教育番組です。様々な「もの、こと、ひと」をキュレーションします。.(n)</desc>
  </programme>
  <programme start="20230313054000 +0000" stop="20230313054500 +0000" channel="フジテレビ">
    <title lang="ja">スワローズ　キッズアカデミー[字]</title>
    <desc lang="ja">野球人気復活に東京ヤクルトが立ち上がる!(n)</desc>
  </programme>
  <programme start="20230313054500 +0000" stop="20230313060000 +0000" channel="フジテレビ">
    <title lang="ja">皇室ご一家[字]</title>
    <desc lang="ja">天皇・皇后両陛下をはじめ天皇ご一家のみなさまのご公務や私的なご旅行、そしてご趣味などをくまなく取材。「皇室」の今をできる限り詳しく紹介します。.(n)</desc>
  </programme>
  <programme start="20230313060000 +0000" stop="20230313061500 +0000" channel="フジテレビ">
    <title lang="ja">FNNニュース[字]</title>
    <desc lang="ja">日曜日の朝は「FNNニュース」。コンパクトながら情報満載。全国のFNN系列の記者がしのぎを削って集めたニュースをしっかりお届けします。.(n)</desc>
  </programme>
  <programme start="20230313061500 +0000" stop="20230313063000 +0000" channel="フジテレビ">
    <title lang="ja">GO!GO!チャギントン[字][二][デ]</title>
    <desc lang="ja">世界で大人気の鉄道CGアニメ「チャギントン」!ナビゲーター:つるの剛士・岸本理沙アナウンサー　他▽声:小林由美子　他▽#549「リーダー・ウィルソン」.(n)</desc>
  </programme>
  <programme start="20230313063000 +0000" stop="20230313070000 +0000" channel="フジテレビ">
    <title lang="ja">はやく起きた朝は・・・[字][解]</title>
    <desc lang="ja">▽大事な用は手紙に限る!▽早く教習所を卒業して!▽野鳥が大好き!▽名もなき家事▽夫に内緒のステーキ▽ジュエリーつけたい!〈出演〉松居直美・磯野貴理子・森尾由美.(n)</desc>
  </programme>
  <programme start="20230313070000 +0000" stop="20230313073000 +0000" channel="フジテレビ">
    <title lang="ja">ボクらの時代[字]</title>
    <desc lang="ja">竹中直人×斎藤工×浅野いにお.(n)</desc>
  </programme>
  <programme start="20230313073000 +0000" stop="20230313085500 +0000" channel="フジテレビ">
    <title lang="ja">日曜報道　THE　PRIME【震災12年…処理水であの国が反発▽被災地に若者】[デ]</title>
    <desc lang="ja">今動いているニュースの「当事者」と、橋下徹がスタジオ生議論!「当事者の考え」が分かる!「日本の行方」が分かる!「dボタン」投票で番組に参加も!(n)</desc>
  </programme>
  <programme start="20230313085500 +0000" stop="20230313090000 +0000" channel="フジテレビ">
    <title lang="ja">千葉の贈り物〜まごころ配達人〜[字][解]</title>
    <desc lang="ja">心のこもった“まごころ"で、全国から訪れる方々を迎えたい…そんな思いを込めて、千葉県のスポットとその魅力を支える人たちを紹介します。.(n)</desc>
  </programme>
  <programme start="20230313090000 +0000" stop="20230313115000 +0000" channel="フジテレビ">
    <title lang="ja">名古屋ウィメンズマラソン2023[デ]</title>
    <desc lang="ja">パリ五輪MGC出場権&amp;世界選手権選考レース!東京五輪代表鈴木亜由子地元で日本記録なるか?前回MGC優勝者前田穂南MGCへ崖っぷち!世界2位チェプンゲティッチ参戦.(n)</desc>
  </programme>
  <programme start="20230313115000 +0000" stop="20230313115500 +0000" channel="フジテレビ">
    <title lang="ja">アレグリア〜バックステージパス〜[字]</title>
    <desc lang="ja">AKB48本田仁美が誘う!シルク・ドゥ・ソレイユ日本公演最新作「アレグリア」の裏側をのぞくバックステージツアー　ここでしか見られない特別映像が満載!(n)</desc>
  </programme>
  <programme start="20230313115500 +0000" stop="20230313120000 +0000" channel="フジテレビ">
    <title lang="ja">FNN　Live　News　days[字]</title>
    <desc lang="ja">週末の昼も「ライブニュース　デイズ」をお見逃しなく。民放で最大級の全国ネットワークを持つFNNの記者が取材したニュースをお届けします。.(n)</desc>
  </programme>
  <programme start="20230313120000 +0000" stop="20230313140000 +0000" channel="フジテレビ">
    <title lang="ja">なりゆき街道旅【館山グルメ満喫!炙り海鮮丼&amp;芋スイーツ!武田真治と絶景温泉へ】[字]</title>
    <desc lang="ja">武田真治と行く、自然溢れる海の街「千葉県・館山」!館山グルメ食べ尽くし!地元食材を使った炙り海鮮丼&amp;新感覚お芋スイーツ!崖観音を参拝&amp;癒しの絶景温泉!(n)</desc>
  </programme>
  <programme start="20230313140000 +0000" stop="20230313145500 +0000" channel="フジテレビ">
    <title lang="ja">ザ・ノンフィクション　新宿二丁目の深夜食堂　前編　〜人生を奏でるビール瓶〜[字]</title>
    <desc lang="ja">新宿二丁目で53年続く深夜食堂を営むのは77歳の名物ママと料理を作る77歳の夫…午前0時オープンの店に訪れるワケあり人生を背負った人々の人生模様を見つめた….(n)</desc>
  </programme>
  <programme start="20230313145500 +0000" stop="20230313150000 +0000" channel="フジテレビ">
    <title lang="ja">ビジネスStyle[字]</title>
    <desc lang="ja">時代を切り拓く企業のトップへのインタビューを始め、商品やサービスなどを多面的に紹介。その理念や哲学からみえてくるビジネスStyleとは?(n)</desc>
  </programme>
  <programme start="20230313150000 +0000" stop="20230313160000 +0000" channel="フジテレビ">
    <title lang="ja">みんなのKEIBA【フィリーズR・GII&amp;アネモネS・L　東西で桜花賞トライアル】</title>
    <desc lang="ja">東西で桜花賞トライアル!阪神「フィリーズレビュー・GII」&amp;中山「アネモネS・L」クラシックへの切符を手にするのは?▽中京「金鯱賞・GII」▽遼河はるひ.(n)</desc>
  </programme>
  <programme start="20230313160000 +0000" stop="20230313160500 +0000" channel="フジテレビ">
    <title lang="ja">ガイド</title>
  </programme>
  <programme start="20230313160500 +0000" stop="20230313172500 +0000" channel="フジテレビ">
    <title lang="ja">坂上・サンドのご当地BET旅in宮城【サンドおすすめ東北絶品グルメが続々!】[字]</title>
    <desc lang="ja">坂上忍とサンドウィッチマンが絶品グルメを食べまくり!ご褒美をかけた“ご当地レース"で真剣予想バトル!坂上ぶちギレ!?「この冬一番震えたロケでした…」.(n)</desc>
  </programme>
  <programme start="20230313172500 +0000" stop="20230313173000 +0000" channel="フジテレビ">
    <title lang="ja">くいしん坊!万才[字][解]</title>
    <desc lang="ja">くいしん坊松岡修造が全国各地の名物料理や郷土の味・珍味に挑戦!その土地の歴史や文化、人々の暮らしにふれ、食べることの喜びや出会いの楽しさを伝えます。.(n)</desc>
  </programme>
  <programme start="20230313173000 +0000" stop="20230313180000 +0000" channel="フジテレビ">
    <title lang="ja">FNN　Live　News　イット![字]</title>
    <desc lang="ja">週末に起きたニュース・スポーツを一挙紹介。どこよりも早く正確な内容で生野陽子・奥寺健・小室瑛莉子の3人のキャスターがお届けします。.(n)</desc>
  </programme>
  <programme start="20230313180000 +0000" stop="20230313183000 +0000" channel="フジテレビ">
    <title lang="ja">ちびまる子ちゃん【富士男の相談にのる/大工の宮ちゃんがやってきたの巻】[字][解][デ]</title>
    <desc lang="ja">〜春が来た!花咲くゲスト声優まつり〜\n「まる子、なぜか富士男の相談にのる」の巻\n「大工の宮ちゃんがやってきた」の巻.(n)</desc>
  </programme>
  <programme start="20230313183000 +0000" stop="20230313190000 +0000" channel="フジテレビ">
    <title lang="ja">サザエさん【行列の店おでん波平/ワカメ、お別れの季節　ほか】[字][解][デ]</title>
    <desc lang="ja">▽行列の店おでん波平\n▽サザエ流、発想術\n▽ワカメ、お別れの季節.(n)</desc>
  </programme>
  <programme start="20230313190000 +0000" stop="20230313210000 +0000" channel="フジテレビ">
    <title lang="ja">千鳥の鬼レンチャン　鬼ハード初代王者は誰だ?視聴者予想SP[字]</title>
    <desc lang="ja">徳永・河邑・chay・丘・nanami・島谷・荒牧・松浦・真麻・May　J.…最初に鬼ハードモードを達成するのは誰だ?視聴者投票ランキングを大発表!(n)</desc>
  </programme>
  <programme start="20230313210000 +0000" stop="20230313215400 +0000" channel="フジテレビ">
    <title lang="ja">呼び出し先生タナカ【あのちゃんVSHiHi猪狩VS島太星!合唱曲頂上決戦!】[字]</title>
    <desc lang="ja">大ブレイク中!あのちゃんVSHiHi猪狩VS大泉洋の後輩!島太星…合唱曲の定番スピッツ「空も飛べるはず」熱唱テスト!超美声&amp;超ヘタ奇跡のデュエット爆誕.(n)</desc>
  </programme>
  <programme start="20230313215400 +0000" stop="20230313220000 +0000" channel="フジテレビ">
    <title lang="ja">1Hセンス[字][解]</title>
    <desc lang="ja">いま輝いている人たちが自分を高める1時間の過ごし方。忙しい彼らの心を満たし活力を生み出す空間、味、絶景とは?自分磨きの達人たちのライフスタイルに迫る。.(n)</desc>
  </programme>
  <programme start="20230313220000 +0000" stop="20230313231500 +0000" channel="フジテレビ">
    <title lang="ja">Mr.サンデー[字]</title>
    <desc lang="ja">脱マスクで需要増加…整形は得か損か?生激論▽令和のルッキズム問題…ありしゃんVS呂布カルマ▽私が「小川さゆり」になったわけ独占密着…家族の日常初取材.(n)</desc>
  </programme>
  <programme start="20230313231500 +0000" stop="20230314003000 +0000" channel="フジテレビ">
    <title lang="ja">S-PARK</title>
    <desc lang="ja">S-PARK▽WBC侍ジャパンの1次Rを証言で検証!第4戦・豪戦は速報&amp;直後の声たっぷり▽3・11佐々木朗希が東北に与えた勇気▽今夜は放送第500回!(n)</desc>
  </programme>
  <programme start="20230313231500 +0000" stop="20230314003000 +0000" channel="フジテレビ">
    <title lang="ja">S-PARK</title>
    <desc lang="ja">S-PARK▽WBC侍ジャパンの1次Rを証言で検証!第4戦・豪戦は速報&amp;直後の声たっぷり▽3・11佐々木朗希が東北に与えた勇気▽今夜は放送第500回!(n)</desc>
  </programme>
  <programme start="20230314003000 +0000" stop="20230314012500 +0000" channel="フジテレビ">
    <title lang="ja">Love　music【aikoがトーク&amp;ライブ!NEWSが話題曲を披露!】[字]</title>
    <desc lang="ja">aikoが「スゴい!」と思った恋愛ソングの歌詞を熱弁!ドラマ主題歌披露▽NEWSが話題曲を特別演出で!▽注目のマルシィとConton　Candyが初登場.(n)</desc>
  </programme>
  <programme start="20230314003000 +0000" stop="20230314012500 +0000" channel="フジテレビ">
    <title lang="ja">Love　music【aikoがトーク&amp;ライブ!NEWSが話題曲を披露!】[字]</title>
    <desc lang="ja">aikoが「スゴい!」と思った恋愛ソングの歌詞を熱弁!ドラマ主題歌披露▽NEWSが話題曲を特別演出で!▽注目のマルシィとConton　Candyが初登場.(n)</desc>
  </programme>
  <programme start="20230314012500 +0000" stop="20230314015500 +0000" channel="フジテレビ">
    <title lang="ja">おかべろ</title>
    <desc lang="ja">超大物・竹中直人がぶっ壊れ!\n俳優・声優・映画監督・コメディアンと謎過ぎる男の経歴と素顔を暴く!\n斎藤工からの暴露も!が、まさかの流れで竹中が壊れちゃう!?(n)</desc>
  </programme>
  <programme start="20230314012500 +0000" stop="20230314015500 +0000" channel="フジテレビ">
    <title lang="ja">おかべろ</title>
    <desc lang="ja">超大物・竹中直人がぶっ壊れ!\n俳優・声優・映画監督・コメディアンと謎過ぎる男の経歴と素顔を暴く!\n斎藤工からの暴露も!が、まさかの流れで竹中が壊れちゃう!?(n)</desc>
  </programme>
  <programme start="20230314015500 +0000" stop="20230314022000 +0000" channel="フジテレビ">
    <title lang="ja">エンタメサーチバラエティ　プレミアの巣窟&lt;サンデーMIDNIGHT&gt;</title>
    <desc lang="ja">ミュージカル「ファインディング・ネバーランド」に出演する武田真治が登場!不朽の名作「ピーターパン」誕生秘話を描いた感動の物語▽アンミカ&amp;チョコプラ対談.(n)</desc>
  </programme>
  <programme start="20230314015500 +0000" stop="20230314022000 +0000" channel="フジテレビ">
    <title lang="ja">エンタメサーチバラエティ　プレミアの巣窟&lt;サンデーMIDNIGHT&gt;</title>
    <desc lang="ja">ミュージカル「ファインディング・ネバーランド」に出演する武田真治が登場!不朽の名作「ピーターパン」誕生秘話を描いた感動の物語▽アンミカ&amp;チョコプラ対談.(n)</desc>
  </programme>
  <programme start="20230314022000 +0000" stop="20230314032000 +0000" channel="フジテレビ">
    <title lang="ja">月曜10時は罠の戦争&lt;サンデーMIDNIGHT&gt;</title>
    <desc lang="ja">鶴巻幹事長(岸部一徳)が手加減なしの猛反撃!鷲津(草ナギ剛)の復讐は全面戦争に発展!事件に関わる政界の闇を白日の下にさらせ!鷹野(小澤征悦)も鶴巻の手先に….(n)</desc>
  </programme>
  <programme start="20230314022000 +0000" stop="20230314032000 +0000" channel="フジテレビ">
    <title lang="ja">月曜10時は罠の戦争&lt;サンデーMIDNIGHT&gt;</title>
    <desc lang="ja">鶴巻幹事長(岸部一徳)が手加減なしの猛反撃!鷲津(草ナギ剛)の復讐は全面戦争に発展!事件に関わる政界の闇を白日の下にさらせ!鷹野(小澤征悦)も鶴巻の手先に….(n)</desc>
  </programme>
  <programme start="20230314032000 +0000" stop="20230314033000 +0000" channel="フジテレビ">
    <title lang="ja">中央競馬ダイジェスト</title>
    <desc lang="ja">日曜日のメインレースをたっぷりとご紹介!更に東京競馬場・中山競馬場の全レースの結果や他場のメインレースの結果もきっちりとお届けしています。競馬ファン必見です!!(n)</desc>
  </programme>
  <programme start="20230314032000 +0000" stop="20230314033000 +0000" channel="フジテレビ">
    <title lang="ja">中央競馬ダイジェスト</title>
    <desc lang="ja">日曜日のメインレースをたっぷりとご紹介!更に東京競馬場・中山競馬場の全レースの結果や他場のメインレースの結果もきっちりとお届けしています。競馬ファン必見です!!(n)</desc>
  </programme>
  <programme start="20230314033000 +0000" stop="20230314040000 +0000" channel="フジテレビ">
    <title lang="ja">ディノスTHEストア</title>
    <desc lang="ja">通販のディノスが自信を持ってお届けする「今がカイドキ!」な商品をご紹介!ゲストの皆さんの本音のリアクションも交えて、商品の魅力を解説します!(n)</desc>
  </programme>
  <programme start="20230314033000 +0000" stop="20230314040000 +0000" channel="フジテレビ">
    <title lang="ja">ディノスTHEストア</title>
    <desc lang="ja">通販のディノスが自信を持ってお届けする「今がカイドキ!」な商品をご紹介!ゲストの皆さんの本音のリアクションも交えて、商品の魅力を解説します!(n)</desc>
  </programme>
  <programme start="20230314040000 +0000" stop="20230314041500 +0000" channel="フジテレビ">
    <title lang="ja">ディノスTHEストア</title>
    <desc lang="ja">通販のディノスが自信を持ってお届けする「今がカイドキ!」な商品をご紹介!ゲストの皆さんの本音のリアクションも交えて、商品の魅力を解説します!(n)</desc>
  </programme>
  <programme start="20230314040000 +0000" stop="20230314041500 +0000" channel="フジテレビ">
    <title lang="ja">ディノスTHEストア</title>
    <desc lang="ja">通販のディノスが自信を持ってお届けする「今がカイドキ!」な商品をご紹介!ゲストの皆さんの本音のリアクションも交えて、商品の魅力を解説します!(n)</desc>
  </programme>
  <programme start="20230314041500 +0000" stop="20230314042500 +0000" channel="フジテレビ">
    <title lang="ja">ディノスTHEストア</title>
    <desc lang="ja">通販のディノスが自信を持ってお届けする「今がカイドキ!」な商品をご紹介!ゲストの皆さんの本音のリアクションも交えて、商品の魅力を解説します!(n)</desc>
  </programme>
  <programme start="20230314041500 +0000" stop="20230314042500 +0000" channel="フジテレビ">
    <title lang="ja">ディノスTHEストア</title>
    <desc lang="ja">通販のディノスが自信を持ってお届けする「今がカイドキ!」な商品をご紹介!ゲストの皆さんの本音のリアクションも交えて、商品の魅力を解説します!(n)</desc>
  </programme>
  <programme start="20230314042500 +0000" stop="20230314045500 +0000" channel="フジテレビ">
    <title lang="ja">ディノスTHEストア</title>
    <desc lang="ja">通販のディノスが自信を持ってお届けする「今がカイドキ!」な商品をご紹介!ゲストの皆さんの本音のリアクションも交えて、商品の魅力を解説します!(n)</desc>
  </programme>
  <programme start="20230314042500 +0000" stop="20230314045500 +0000" channel="フジテレビ">
    <title lang="ja">ディノスTHEストア</title>
    <desc lang="ja">通販のディノスが自信を持ってお届けする「今がカイドキ!」な商品をご紹介!ゲストの皆さんの本音のリアクションも交えて、商品の魅力を解説します!(n)</desc>
  </programme>
  <programme start="20230314045500 +0000" stop="20230314052500 +0000" channel="フジテレビ">
    <title lang="ja">めざましテレビ全部見せ[デ]</title>
    <desc lang="ja">きょうのめざましテレビで注目しているとっておきのニュース&amp;スポーツ&amp;エンタメが全部わかります!▽更新されたばかりの最新お天気情報をチェック▽占い.(n)</desc>
  </programme>
  <programme start="20230314052500 +0000" stop="20230314080000 +0000" channel="フジテレビ">
    <title lang="ja">めざましテレビ[デ]</title>
    <desc lang="ja">ニュース&amp;スポーツにエンタメ&amp;トレンド家族で見たい新情報のシャワー▽ココ調で身近な疑問検証▽めざましじゃんけん▽きょうのわんこ▽紙兎ロペ▽占い.(n)</desc>
  </programme>
  <programme start="20230314080000 +0000" stop="20230314095000 +0000" channel="フジテレビ">
    <title lang="ja">めざまし8[字][デ]</title>
    <desc lang="ja">谷原章介&amp;永島優美と新しい朝を始めよう!目が覚める今日一番のニュースをしっかり伝えます!当事者たちを独自取材。わかるまで解説します。天達が天気を深掘り!(n)</desc>
  </programme>
  <programme start="20230314095000 +0000" stop="20230314112500 +0000" channel="フジテレビ">
    <title lang="ja">ノンストップ![字][デ]</title>
    <desc lang="ja">MCバナナマン設楽統▽今役立つ生活情報&amp;バズな話題&amp;気になるあの人&amp;旬なエンタメ情報を独自な目線で!▽本音トーク!せきららスタジオ.(n)</desc>
  </programme>
  <programme start="20230314112500 +0000" stop="20230314113000 +0000" channel="フジテレビ">
    <title lang="ja">国分太一の気ままにさんぽ[字][解]</title>
    <desc lang="ja">おさんぽ歴10年目に突入した国分太一。もはや「さんぽの達人」の域まで達したこの男が、五感を使った新たな独自の目線で日本全国を気ままにおさんぽします!!(n)</desc>
  </programme>
  <programme start="20230314113000 +0000" stop="20230314114500 +0000" channel="フジテレビ">
    <title lang="ja">FNN　Live　News　days[字]</title>
    <desc lang="ja">世の中の動きを素早くキャッチ!最新ニュースをわかりやすく、丁寧にお届けします。気になるポイントは深掘りして、役に立つニュースをお伝えします。.(n)</desc>
  </programme>
  <programme start="20230314114500 +0000" stop="20230314144500 +0000" channel="フジテレビ">
    <title lang="ja">ぽかぽか[字]</title>
    <desc lang="ja">ハライチ&amp;神田愛花がお送りするお昼の新バラエティ!豪華ゲストとのトーク企画にスタジオショー!さらには笑えるVTRコーナーも!?“ぽかぽか"なお昼を是非.(n)</desc>
  </programme>
  <programme start="20230314144500 +0000" stop="20230314154500 +0000" channel="フジテレビ">
    <title lang="ja">ライアーゲーム　シーズン2　#06[再][字][デ]</title>
    <desc lang="ja">最強のライバル葛城の作戦に全プレイヤー服従…瀕死のナオと秋山、「ヴァシリスキー回路」で奇跡の逆転なるか?戸田恵梨香　松田翔太・菊地凛子・吉瀬美智子　渡辺いっけい.(n)</desc>
  </programme>
  <programme start="20230314154500 +0000" stop="20230314190000 +0000" channel="フジテレビ">
    <title lang="ja">イット![字][デ]</title>
    <desc lang="ja">ソレ知りたいを速報!榎並大二郎&amp;宮司愛海が現場と生の声を取材。わかりやすく伝えます▽ガチャピンとあしたの空を先読み!▽人気企画「しらべてみたら」.(n)</desc>
  </programme>
  <programme start="20230314190000 +0000" stop="20230314210000 +0000" channel="フジテレビ">
    <title lang="ja">ネプリーグSP菜々緒率いる人気俳優軍vsGENERATIONSvs人気芸人![字][デ]</title>
    <desc lang="ja">木10ドラマが盤石の布陣で参戦!対するはGENERATIONS全員とぺこぱ&amp;ロッチ!数原VS片寄の身内バトルも必見!▼dボタンで石垣牛ハンバーグ当たる.(n)</desc>
  </programme>
  <programme start="20230314210000 +0000" stop="20230314215400 +0000" channel="フジテレビ">
    <title lang="ja">女神の教室【衝撃のクライマックス!そして柊木、最後の講義へ!!】　#10[字][解][デ]</title>
    <desc lang="ja">[衝撃のクライマックスへ!]藍井と風見、二人の間に何があったのか?全てが結びつく事件の行方とは?そして、柊木ロースクール最後の講義へ!!(n)</desc>
  </programme>
  <programme start="20230314215400 +0000" stop="20230314220000 +0000" channel="フジテレビ">
    <title lang="ja">四季彩キッチン[字]</title>
    <desc lang="ja">林修先生が“旬の食材"を入口に日本の農業の“いま"をプレゼンテーション!今回は、神奈川県オリジナルの柑橘ブランド「湘南ゴールド」を紹介します。.(n)</desc>
  </programme>
  <programme start="20230314220000 +0000" stop="20230314225400 +0000" channel="フジテレビ">
    <title lang="ja">罠の戦争【復讐果たす大逆転劇!宿敵に制裁を!政界に激震…最終章へ】　#09[字][デ]</title>
    <desc lang="ja">政界激震で急展開!新人議員VS幹事長の熾烈な騙し合い!鷲津(草ナギ剛)に鶴巻幹事長(岸部一徳)を潰すチャンス到来!復讐を果たす大逆転劇が巻き起こる…物語は最終章へ.(n)</desc>
  </programme>
  <programme start="20230314225400 +0000" stop="20230314230000 +0000" channel="フジテレビ">
    <title lang="ja">体感!サステナWAVE【捨てる食用油がカラフルなキャンドルに】[字]</title>
    <desc lang="ja">使い終わった食用油を簡単に、オシャレにリサイクル!クレヨンを溶かしてカラフルなキャンドルを作ろう。小室瑛莉子アナウンサーが体感します!(n)</desc>
  </programme>
  <programme start="20230314230000 +0000" stop="20230314234000 +0000" channel="フジテレビ">
    <title lang="ja">突然ですが占ってもいいですか?【北川景子(秘)私生活!池松壮亮&amp;浜辺美波&amp;柄本佑】[字]</title>
    <desc lang="ja">北川景子「どうしよう、暴かれる…」(秘)夫婦関係…子育て…(秘)私生活を赤裸々占い!▽池松壮亮の手相に星ひとみ三度見!?まさかの(秘)本性に浜辺美波&amp;柄本佑も爆笑!(n)</desc>
  </programme>
  <programme start="20230314045500 +0000" stop="20230314231500 +0000" channel="フジテレビ">
    <title lang="ja">めざましテレビ全部見せ[デ]</title>
    <desc lang="ja">きょうのめざましテレビで注目しているとっておきのニュース&amp;スポーツ&amp;エンタメが全部わかります!▽更新されたばかりの最新お天気情報をチェック▽占い.(n)</desc>
  </programme>
  <programme start="20230314234000 +0000" stop="20230315002500 +0000" channel="フジテレビ">
    <title lang="ja">FNN　Live　News　α[字]</title>
    <desc lang="ja">働く人に役立つ情報を+αして、その日のニュースをコンパクトにお伝えします。キャスターは月〜水曜日が内田嶺衣奈、木〜金曜日は小澤陽子。.(n)</desc>
  </programme>
  <programme start="20230314234000 +0000" stop="20230315002500 +0000" channel="フジテレビ">
    <title lang="ja">FNN　Live　News　α[字]</title>
    <desc lang="ja">働く人に役立つ情報を+αして、その日のニュースをコンパクトにお伝えします。キャスターは月〜水曜日が内田嶺衣奈、木〜金曜日は小澤陽子。.(n)</desc>
  </programme>
  <programme start="20230315002500 +0000" stop="20230315005500 +0000" channel="フジテレビ">
    <title lang="ja">THEスピリット〜闘魂レスラー発掘プロジェクト〜&lt;月曜PLUS!&gt;</title>
    <desc lang="ja">ついに結果発表!合格したのは誰だ…!?「悔しいよな」予想だにしていなかった結末にオカダ・カズチカが涙…新日本プロレス新人発掘プロジェクトついに完結.(n)</desc>
  </programme>
  <programme start="20230315002500 +0000" stop="20230315005500 +0000" channel="フジテレビ">
    <title lang="ja">THEスピリット〜闘魂レスラー発掘プロジェクト〜&lt;月曜PLUS!&gt;</title>
    <desc lang="ja">ついに結果発表!合格したのは誰だ…!?「悔しいよな」予想だにしていなかった結末にオカダ・カズチカが涙…新日本プロレス新人発掘プロジェクトついに完結.(n)</desc>
  </programme>
  <programme start="20230315005500 +0000" stop="20230315012500 +0000" channel="フジテレビ">
    <title lang="ja">関ジャニ∞の　あとはご自由に</title>
    <desc lang="ja">たった一つだけのルールを設定して「あとはご自由に」と、ゲストと関ジャニ∞が多彩な企画にチャレンジ!企画から生まれる様々な化学反応をお届けします!(n)</desc>
  </programme>
  <programme start="20230315005500 +0000" stop="20230315012500 +0000" channel="フジテレビ">
    <title lang="ja">関ジャニ∞の　あとはご自由に</title>
    <desc lang="ja">たった一つだけのルールを設定して「あとはご自由に」と、ゲストと関ジャニ∞が多彩な企画にチャレンジ!企画から生まれる様々な化学反応をお届けします!(n)</desc>
  </programme>
  <programme start="20230315012500 +0000" stop="20230315015500 +0000" channel="フジテレビ">
    <title lang="ja">[終]恋と友情のあいだで(廉Ver.)&lt;Mナイト&gt;　#05</title>
    <desc lang="ja">恋と友情のあいだで、彷徨い続けて.(n)</desc>
  </programme>
  <programme start="20230315012500 +0000" stop="20230315015500 +0000" channel="フジテレビ">
    <title lang="ja">[終]恋と友情のあいだで(廉Ver.)&lt;Mナイト&gt;　#05</title>
    <desc lang="ja">恋と友情のあいだで、彷徨い続けて.(n)</desc>
  </programme>
  <programme start="20230315015500 +0000" stop="20230315022000 +0000" channel="フジテレビ">
    <title lang="ja">魔女に言われたい夜〜正直過ぎる品定め〜&lt;Mナイト&gt;</title>
    <desc lang="ja">川島明(麒麟)が深夜にお届けするリアルトーク通販バラエティ!美容・健康・家電・コスメ・ファッションなどをゲストと徹底的に品定め&amp;ぶっちゃけトーク!(n)</desc>
  </programme>
  <programme start="20230315015500 +0000" stop="20230315022000 +0000" channel="フジテレビ">
    <title lang="ja">魔女に言われたい夜〜正直過ぎる品定め〜&lt;Mナイト&gt;</title>
    <desc lang="ja">川島明(麒麟)が深夜にお届けするリアルトーク通販バラエティ!美容・健康・家電・コスメ・ファッションなどをゲストと徹底的に品定め&amp;ぶっちゃけトーク!(n)</desc>
  </programme>
  <programme start="20230315022000 +0000" stop="20230315023500 +0000" channel="フジテレビ">
    <title lang="ja">永久少年　Eternal　Boys&lt;Mナイト&gt;　#22</title>
    <desc lang="ja">アルバム.(n)</desc>
  </programme>
  <programme start="20230315022000 +0000" stop="20230315023500 +0000" channel="フジテレビ">
    <title lang="ja">永久少年　Eternal　Boys&lt;Mナイト&gt;　#22</title>
    <desc lang="ja">アルバム.(n)</desc>
  </programme>
  <programme start="20230315023500 +0000" stop="20230315032000 +0000" channel="フジテレビ">
    <title lang="ja">サーチ〜運命の分岐点〜&lt;Mナイト&gt;【蘇った映像】　#11</title>
    <desc lang="ja">「ノクドゥ伝〜花に降る月明り〜」のチャン・ドンユンとガールズグループf(x)クリスタル(チョン・スジョン)が事件を捜査する特殊任務隊として共演!(n)</desc>
  </programme>
  <programme start="20230315023500 +0000" stop="20230315032000 +0000" channel="フジテレビ">
    <title lang="ja">サーチ〜運命の分岐点〜&lt;Mナイト&gt;【蘇った映像】　#11</title>
    <desc lang="ja">「ノクドゥ伝〜花に降る月明り〜」のチャン・ドンユンとガールズグループf(x)クリスタル(チョン・スジョン)が事件を捜査する特殊任務隊として共演!(n)</desc>
  </programme>
  <programme start="20230315032000 +0000" stop="20230315035000 +0000" channel="フジテレビ">
    <title lang="ja">ディノスTHEストア</title>
    <desc lang="ja">通販のディノスが自信を持ってお届けする「今がカイドキ!」な商品をご紹介!ゲストの皆さんの本音のリアクションも交えて、商品の魅力を解説します!(n)</desc>
  </programme>
  <programme start="20230315032000 +0000" stop="20230315035000 +0000" channel="フジテレビ">
    <title lang="ja">ディノスTHEストア</title>
    <desc lang="ja">通販のディノスが自信を持ってお届けする「今がカイドキ!」な商品をご紹介!ゲストの皆さんの本音のリアクションも交えて、商品の魅力を解説します!(n)</desc>
  </programme>
  <programme start="20230315035000 +0000" stop="20230315041000 +0000" channel="フジテレビ">
    <title lang="ja">ディノスTHEストア</title>
    <desc lang="ja">通販のディノスが自信を持ってお届けする「今がカイドキ!」な商品をご紹介!ゲストの皆さんの本音のリアクションも交えて、商品の魅力を解説します!(n)</desc>
  </programme>
  <programme start="20230315035000 +0000" stop="20230315041000 +0000" channel="フジテレビ">
    <title lang="ja">ディノスTHEストア</title>
    <desc lang="ja">通販のディノスが自信を持ってお届けする「今がカイドキ!」な商品をご紹介!ゲストの皆さんの本音のリアクションも交えて、商品の魅力を解説します!(n)</desc>
  </programme>
  <programme start="20230315041000 +0000" stop="20230315042500 +0000" channel="フジテレビ">
    <title lang="ja">ディノスTHEストア</title>
    <desc lang="ja">通販のディノスが自信を持ってお届けする「今がカイドキ!」な商品をご紹介!ゲストの皆さんの本音のリアクションも交えて、商品の魅力を解説します!(n)</desc>
  </programme>
  <programme start="20230315041000 +0000" stop="20230315042500 +0000" channel="フジテレビ">
    <title lang="ja">ディノスTHEストア</title>
    <desc lang="ja">通販のディノスが自信を持ってお届けする「今がカイドキ!」な商品をご紹介!ゲストの皆さんの本音のリアクションも交えて、商品の魅力を解説します!(n)</desc>
  </programme>
  <programme start="20230315042500 +0000" stop="20230315045500 +0000" channel="フジテレビ">
    <title lang="ja">ディノスTHEストア</title>
    <desc lang="ja">通販のディノスが自信を持ってお届けする「今がカイドキ!」な商品をご紹介!ゲストの皆さんの本音のリアクションも交えて、商品の魅力を解説します!(n)</desc>
  </programme>
  <programme start="20230315042500 +0000" stop="20230315045500 +0000" channel="フジテレビ">
    <title lang="ja">ディノスTHEストア</title>
    <desc lang="ja">通販のディノスが自信を持ってお届けする「今がカイドキ!」な商品をご紹介!ゲストの皆さんの本音のリアクションも交えて、商品の魅力を解説します!(n)</desc>
  </programme>
  <programme start="20230315045500 +0000" stop="20230315052500 +0000" channel="フジテレビ">
    <title lang="ja">めざましテレビ全部見せ[デ]</title>
    <desc lang="ja">きょうのめざましテレビで注目しているとっておきのニュース&amp;スポーツ&amp;エンタメが全部わかります!▽更新されたばかりの最新お天気情報をチェック▽占い.(n)</desc>
  </programme>
  <programme start="20230315052500 +0000" stop="20230315080000 +0000" channel="フジテレビ">
    <title lang="ja">めざましテレビ[デ]</title>
    <desc lang="ja">ニュース&amp;スポーツにエンタメ&amp;トレンド家族で見たい新情報のシャワー▽ココ調で身近な疑問検証▽めざましじゃんけん▽きょうのわんこ▽紙兎ロペ▽占い.(n)</desc>
  </programme>
  <programme start="20230315080000 +0000" stop="20230315095000 +0000" channel="フジテレビ">
    <title lang="ja">めざまし8[字][デ]</title>
    <desc lang="ja">谷原章介&amp;永島優美と新しい朝を始めよう!目が覚める今日一番のニュースをしっかり伝えます!当事者たちを独自取材。わかるまで解説します。天達が天気を深掘り!(n)</desc>
  </programme>
  <programme start="20230315095000 +0000" stop="20230315112500 +0000" channel="フジテレビ">
    <title lang="ja">ノンストップ![字][デ]</title>
    <desc lang="ja">MCバナナマン設楽統▽今役立つ生活情報&amp;バズな話題&amp;気になるあの人&amp;旬なエンタメ情報を独自な目線で!▽本音トーク!せきららスタジオ.(n)</desc>
  </programme>
  <programme start="20230315112500 +0000" stop="20230315113000 +0000" channel="フジテレビ">
    <title lang="ja">国分太一の気ままにさんぽ[字][解]</title>
    <desc lang="ja">おさんぽ歴10年目に突入した国分太一。もはや「さんぽの達人」の域まで達したこの男が、五感を使った新たな独自の目線で日本全国を気ままにおさんぽします!!(n)</desc>
  </programme>
  <programme start="20230315113000 +0000" stop="20230315114500 +0000" channel="フジテレビ">
    <title lang="ja">FNN　Live　News　days[字]</title>
    <desc lang="ja">世の中の動きを素早くキャッチ!最新ニュースをわかりやすく、丁寧にお届けします。気になるポイントは深掘りして、役に立つニュースをお伝えします。.(n)</desc>
  </programme>
  <programme start="20230315114500 +0000" stop="20230315144500 +0000" channel="フジテレビ">
    <title lang="ja">ぽかぽか[字]</title>
    <desc lang="ja">ハライチ&amp;神田愛花がお送りするお昼の新バラエティ!豪華ゲストとのトーク企画にスタジオショー!さらには笑えるVTRコーナーも!?“ぽかぽか"なお昼を是非.(n)</desc>
  </programme>
  <programme start="20230315144500 +0000" stop="20230315154500 +0000" channel="フジテレビ">
    <title lang="ja">ライアーゲーム　シーズン2　#07[再][字][デ]</title>
    <desc lang="ja">秋山vs葛城ついに決着!?天才葛城がナオに死を宣告…そして「あの男」も登場!秋山を崩壊させる切り札とは?戸田恵梨香　松田翔太・菊地凛子・吉瀬美智子　渡辺いっけい.(n)</desc>
  </programme>
  <programme start="20230315154500 +0000" stop="20230315190000 +0000" channel="フジテレビ">
    <title lang="ja">イット![字][デ]</title>
    <desc lang="ja">ソレ知りたいを速報!榎並大二郎&amp;宮司愛海が現場と生の声を取材。わかりやすく伝えます▽ガチャピンとあしたの空を先読み!▽人気企画「しらべてみたら」.(n)</desc>
  </programme>
  <programme start="20230315190000 +0000" stop="20230315210000 +0000" channel="フジテレビ">
    <title lang="ja">今夜はナゾトレ桜開花直前!花の知識王決定戦&amp;日光東照宮!徳川家康の謎2HSP[字][デ]</title>
    <desc lang="ja">花の絶景名所2時間SP!日本全国!桜名所連発▽日光東照宮からも出題!徳川家康がわかる謎Q▽戸次重幸が全力珍解答!?習ったはずが忘れている…日本の常識で老化防止.(n)</desc>
  </programme>
  <programme start="20230315210000 +0000" stop="20230315215400 +0000" channel="フジテレビ">
    <title lang="ja">所JAPAN【中華の王者バーミヤンvs名店が教える!私のここイチ中華(秘)名店】[字]</title>
    <desc lang="ja">全国354店舗!中華チェーン・バーミヤン人気の秘密▽女性客が殺到(秘)ラーメン▽彦摩呂も愛用!業界初〇〇サービス▽名店シェフが教える!私のここ一番中華店▽バカリズム.(n)</desc>
  </programme>
  <programme start="20230315215400 +0000" stop="20230315220000 +0000" channel="フジテレビ">
    <title lang="ja">My　Routine〜太陽と星空の時間〜[字]</title>
    <desc lang="ja">100歳まで健康に!各界で活躍するあの有名人の独自の健康法〜マイ・ルーティーンをこっそり教えます!▽俳優・金子貴俊.(n)</desc>
  </programme>
  <programme start="20230315220000 +0000" stop="20230315225400 +0000" channel="フジテレビ">
    <title lang="ja">火曜は全力!華大さんと千鳥くん【SnowMan目黒蓮はスパイ?にこるん名推理】[字]</title>
    <desc lang="ja">スパイ7分の1にSnow　Man目黒蓮&amp;藤田ニコル参戦!大ヒットドラマ「silent」の名場面を目黒が再現?にこるん名推理に華丸もタジタジ!ノブまたも冤罪か?(n)</desc>
  </programme>
  <programme start="20230315225400 +0000" stop="20230315230000 +0000" channel="フジテレビ">
    <title lang="ja">地球との約束〜心に刻む景色〜[字]</title>
    <desc lang="ja">東京都青梅市・吉野梅郷　今よみがえる梅の郷.(n)</desc>
  </programme>
  <programme start="20230315230000 +0000" stop="20230315233000 +0000" channel="フジテレビ">
    <title lang="ja">セブンルール【女優・今田美桜に密着!26歳、等身大な日々と笑顔】[字][解]</title>
    <desc lang="ja">お正月の帰省、旧友とのランチ、家族との電話、撮影の合間…今田美桜が見せるリアルな素顔と笑顔.(n)</desc>
  </programme>
  <programme start="20230315233000 +0000" stop="20230315234000 +0000" channel="フジテレビ">
    <title lang="ja">乃木坂46とダンスバトルズ[字]</title>
    <desc lang="ja">乃木坂46とダンスバトルズ.(n)</desc>
  </programme>
  <programme start="20230315045500 +0000" stop="20230315234000 +0000" channel="フジテレビ">
    <title lang="ja">めざましテレビ全部見せ[デ]</title>
    <desc lang="ja">きょうのめざましテレビで注目しているとっておきのニュース&amp;スポーツ&amp;エンタメが全部わかります!▽更新されたばかりの最新お天気情報をチェック▽占い.(n)</desc>
  </programme>
  <programme start="20230315234000 +0000" stop="20230316002500 +0000" channel="フジテレビ">
    <title lang="ja">FNN　Live　News　α[字]</title>
    <desc lang="ja">働く人に役立つ情報を+αして、その日のニュースをコンパクトにお伝えします。キャスターは月〜水曜日が内田嶺衣奈、木〜金曜日は小澤陽子。.(n)</desc>
  </programme>
  <programme start="20230315234000 +0000" stop="20230316002500 +0000" channel="フジテレビ">
    <title lang="ja">FNN　Live　News　α[字]</title>
    <desc lang="ja">働く人に役立つ情報を+αして、その日のニュースをコンパクトにお伝えします。キャスターは月〜水曜日が内田嶺衣奈、木〜金曜日は小澤陽子。.(n)</desc>
  </programme>
  <programme start="20230316002500 +0000" stop="20230316005500 +0000" channel="フジテレビ">
    <title lang="ja">#who　am　I&lt;火曜ACTION!&gt;【“エグすぎる"考察型SNSサスペンス】</title>
    <desc lang="ja">関水渚主演!“エグすぎる"考察型SNSサスペンス、波乱の第2話!突き落とされて記憶を失った女子大生が、自分のアカウントから犯人と「本当の自分」を探す!(n)</desc>
  </programme>
  <programme start="20230316002500 +0000" stop="20230316005500 +0000" channel="フジテレビ">
    <title lang="ja">#who　am　I&lt;火曜ACTION!&gt;【“エグすぎる"考察型SNSサスペンス】</title>
    <desc lang="ja">関水渚主演!“エグすぎる"考察型SNSサスペンス、波乱の第2話!突き落とされて記憶を失った女子大生が、自分のアカウントから犯人と「本当の自分」を探す!(n)</desc>
  </programme>
  <programme start="20230316005500 +0000" stop="20230316012500 +0000" channel="フジテレビ">
    <title lang="ja">ステキな二番煎じ!!&lt;火曜NEXT!&gt;</title>
    <desc lang="ja">MC尾上松也…昭和・平成に大ヒットしたモノを令和の時代にもう一度!今回番組が目を付けたのは大流行したカルチャー…鬼越&amp;とうあがこのプロジェクトに挑む!(n)</desc>
  </programme>
  <programme start="20230316005500 +0000" stop="20230316012500 +0000" channel="フジテレビ">
    <title lang="ja">ステキな二番煎じ!!&lt;火曜NEXT!&gt;</title>
    <desc lang="ja">MC尾上松也…昭和・平成に大ヒットしたモノを令和の時代にもう一度!今回番組が目を付けたのは大流行したカルチャー…鬼越&amp;とうあがこのプロジェクトに挑む!(n)</desc>
  </programme>
  <programme start="20230316012500 +0000" stop="20230316022500 +0000" channel="フジテレビ">
    <title lang="ja">スタンドUPスタート&lt;Tナイト&gt;　#08[再][字][解]</title>
    <desc lang="ja">高島は定年退職した先輩の轟の再就職先を紹介してくれと大陽に頼む。高島が三ツ星に戻ると経産省から天下りしてきた篠田が新たに社長室長になることを告げられる.(n)</desc>
  </programme>
  <programme start="20230316012500 +0000" stop="20230316022500 +0000" channel="フジテレビ">
    <title lang="ja">スタンドUPスタート&lt;Tナイト&gt;　#08[再][字][解]</title>
    <desc lang="ja">高島は定年退職した先輩の轟の再就職先を紹介してくれと大陽に頼む。高島が三ツ星に戻ると経産省から天下りしてきた篠田が新たに社長室長になることを告げられる.(n)</desc>
  </programme>
  <programme start="20230316022500 +0000" stop="20230316035500 +0000" channel="フジテレビ">
    <title lang="ja">寺門ジモンの取材拒否の店2023春&lt;Tナイト&gt;</title>
    <desc lang="ja">東西の幻の絶品ステーキが揃い踏み!西の横綱・日本最高峰の窯焼きステーキ&amp;東の新鋭・有名シェフが手掛ける新感覚ステーキ▽焼肉・ラーメン・蟹料理…隠れた名店が続々!(n)</desc>
  </programme>
  <programme start="20230316022500 +0000" stop="20230316035500 +0000" channel="フジテレビ">
    <title lang="ja">寺門ジモンの取材拒否の店2023春&lt;Tナイト&gt;</title>
    <desc lang="ja">東西の幻の絶品ステーキが揃い踏み!西の横綱・日本最高峰の窯焼きステーキ&amp;東の新鋭・有名シェフが手掛ける新感覚ステーキ▽焼肉・ラーメン・蟹料理…隠れた名店が続々!(n)</desc>
  </programme>
  <programme start="20230316035500 +0000" stop="20230316042500 +0000" channel="フジテレビ">
    <title lang="ja">ディノスTHEストア</title>
    <desc lang="ja">通販のディノスが自信を持ってお届けする「今がカイドキ!」な商品をご紹介!ゲストの皆さんの本音のリアクションも交えて、商品の魅力を解説します!(n)</desc>
  </programme>
  <programme start="20230316035500 +0000" stop="20230316042500 +0000" channel="フジテレビ">
    <title lang="ja">ディノスTHEストア</title>
    <desc lang="ja">通販のディノスが自信を持ってお届けする「今がカイドキ!」な商品をご紹介!ゲストの皆さんの本音のリアクションも交えて、商品の魅力を解説します!(n)</desc>
  </programme>
  <programme start="20230316042500 +0000" stop="20230316045500 +0000" channel="フジテレビ">
    <title lang="ja">ディノスTHEストア</title>
    <desc lang="ja">通販のディノスが自信を持ってお届けする「今がカイドキ!」な商品をご紹介!ゲストの皆さんの本音のリアクションも交えて、商品の魅力を解説します!(n)</desc>
  </programme>
  <programme start="20230316042500 +0000" stop="20230316045500 +0000" channel="フジテレビ">
    <title lang="ja">ディノスTHEストア</title>
    <desc lang="ja">通販のディノスが自信を持ってお届けする「今がカイドキ!」な商品をご紹介!ゲストの皆さんの本音のリアクションも交えて、商品の魅力を解説します!(n)</desc>
  </programme>
  <programme start="20230316045500 +0000" stop="20230316052500 +0000" channel="フジテレビ">
    <title lang="ja">めざましテレビ全部見せ[デ]</title>
    <desc lang="ja">きょうのめざましテレビで注目しているとっておきのニュース&amp;スポーツ&amp;エンタメが全部わかります!▽更新されたばかりの最新お天気情報をチェック▽占い.(n)</desc>
  </programme>
  <programme start="20230316052500 +0000" stop="20230316080000 +0000" channel="フジテレビ">
    <title lang="ja">めざましテレビ[デ]</title>
    <desc lang="ja">ニュース&amp;スポーツにエンタメ&amp;トレンド家族で見たい新情報のシャワー▽ココ調で身近な疑問検証▽めざましじゃんけん▽きょうのわんこ▽紙兎ロペ▽占い.(n)</desc>
  </programme>
  <programme start="20230316080000 +0000" stop="20230316095000 +0000" channel="フジテレビ">
    <title lang="ja">めざまし8[字][デ]</title>
    <desc lang="ja">谷原章介&amp;永島優美と新しい朝を始めよう!目が覚める今日一番のニュースをしっかり伝えます!当事者たちを独自取材。わかるまで解説します。天達が天気を深掘り!(n)</desc>
  </programme>
  <programme start="20230316095000 +0000" stop="20230316112500 +0000" channel="フジテレビ">
    <title lang="ja">ノンストップ![字][デ]</title>
    <desc lang="ja">MCバナナマン設楽統▽今役立つ生活情報&amp;バズな話題&amp;気になるあの人&amp;旬なエンタメ情報を独自な目線で!▽本音トーク!せきららスタジオ.(n)</desc>
  </programme>
  <programme start="20230316112500 +0000" stop="20230316113000 +0000" channel="フジテレビ">
    <title lang="ja">国分太一の気ままにさんぽ[字][解]</title>
    <desc lang="ja">おさんぽ歴10年目に突入した国分太一。もはや「さんぽの達人」の域まで達したこの男が、五感を使った新たな独自の目線で日本全国を気ままにおさんぽします!!(n)</desc>
  </programme>
  <programme start="20230316113000 +0000" stop="20230316114500 +0000" channel="フジテレビ">
    <title lang="ja">FNN　Live　News　days[字]</title>
    <desc lang="ja">世の中の動きを素早くキャッチ!最新ニュースをわかりやすく、丁寧にお届けします。気になるポイントは深掘りして、役に立つニュースをお伝えします。.(n)</desc>
  </programme>
  <programme start="20230316114500 +0000" stop="20230316144500 +0000" channel="フジテレビ">
    <title lang="ja">ぽかぽか[字]</title>
    <desc lang="ja">ハライチ&amp;神田愛花がお送りするお昼の新バラエティ!豪華ゲストとのトーク企画にスタジオショー!さらには笑えるVTRコーナーも!?“ぽかぽか"なお昼を是非.(n)</desc>
  </programme>
  <programme start="20230316144500 +0000" stop="20230316154500 +0000" channel="フジテレビ">
    <title lang="ja">ライアーゲーム　シーズン2　#08[再][字][デ]</title>
    <desc lang="ja">ライアーゲーム最終回まであと2回!ついに後半戦ゴールドラッシュゲーム開始、そして秋山と葛城の衝撃の過去が明らかに!戸田恵梨香　松田翔太.(n)</desc>
  </programme>
  <programme start="20230316154500 +0000" stop="20230316190000 +0000" channel="フジテレビ">
    <title lang="ja">イット![字][デ]</title>
    <desc lang="ja">ソレ知りたいを速報!榎並大二郎&amp;宮司愛海が現場と生の声を取材。わかりやすく伝えます▽ガチャピンとあしたの空を先読み!▽人気企画「しらべてみたら」.(n)</desc>
  </programme>
  <programme start="20230316190000 +0000" stop="20230316210000 +0000" channel="フジテレビ">
    <title lang="ja">世界の何だコレ!?ミステリーSP[字]</title>
    <desc lang="ja">▽全米が震撼!IQ167の連続爆弾魔、FBIが18年追った“ユナボマー"とは?▽インターネットで今も語り継がれる都市伝説、大学生が迷い込んだ“山の牧場"とは!?(n)</desc>
  </programme>
  <programme start="20230316210000 +0000" stop="20230316215400 +0000" channel="フジテレビ">
    <title lang="ja">ホンマでっか!?TV[字]</title>
    <desc lang="ja">お酒を飲まないとやってられない人、集団人生相談!\n大悟、ラーメンに肘を突っ込みながら寝てしまった!?高橋ひとみ、酔うと別人格「みゆき」が目覚める!?(n)</desc>
  </programme>
  <programme start="20230316215400 +0000" stop="20230316220000 +0000" channel="フジテレビ">
    <title lang="ja">おふくろ、もう一杯[字]</title>
    <desc lang="ja">「もう一杯!」と思わず言ってしまうようなカツオ・昆布・いりこなどの出汁(だし)が効いた日本全国のこだわり料理を紹介します.(n)</desc>
  </programme>
  <programme start="20230316220000 +0000" stop="20230316225400 +0000" channel="フジテレビ">
    <title lang="ja">スタンドUPスタート【人に価値は必要か?新たな出会いと過去の傷】　#09[字][解][デ]</title>
    <desc lang="ja">大陽は義知に言われた「ある事」で自信喪失してしまう。大学研究員の河野と三上は大陽に出資を求めるが反応が芳しくない。そこに八神という謎の男がやってくる。.(n)</desc>
  </programme>
  <programme start="20230316225400 +0000" stop="20230316230000 +0000" channel="フジテレビ">
    <title lang="ja">フューチャーランナーズ〜17の未来〜【SDGsの課題解決に取り組む人に密着!】[字]</title>
    <desc lang="ja">2006年にアフリカのザンビアを訪れたエクベリさんは、貧困問題の解決のため、バナナの茎の繊維から紙を作り出す事業を立ち上げました。その取り組みとは?(n)</desc>
  </programme>
  <programme start="20230316230000 +0000" stop="20230316234000 +0000" channel="フジテレビ">
    <title lang="ja">TOKIOカケル[字]</title>
    <desc lang="ja">今回の“友達ゲスト"は、俳優の池松壮亮!そして“エンジェルちゃん"として、相席スタートの山崎ケイが登場!(n)</desc>
  </programme>
  <programme start="20230316045500 +0000" stop="20230316234000 +0000" channel="フジテレビ">
    <title lang="ja">めざましテレビ全部見せ[デ]</title>
    <desc lang="ja">きょうのめざましテレビで注目しているとっておきのニュース&amp;スポーツ&amp;エンタメが全部わかります!▽更新されたばかりの最新お天気情報をチェック▽占い.(n)</desc>
  </programme>
  <programme start="20230316234000 +0000" stop="20230317002500 +0000" channel="フジテレビ">
    <title lang="ja">FNN　Live　News　α[字]</title>
    <desc lang="ja">働く人に役立つ情報を+αして、その日のニュースをコンパクトにお伝えします。キャスターは月〜水曜日が内田嶺衣奈、木〜金曜日は小澤陽子。.(n)</desc>
  </programme>
  <programme start="20230316234000 +0000" stop="20230317002500 +0000" channel="フジテレビ">
    <title lang="ja">FNN　Live　News　α[字]</title>
    <desc lang="ja">働く人に役立つ情報を+αして、その日のニュースをコンパクトにお伝えします。キャスターは月〜水曜日が内田嶺衣奈、木〜金曜日は小澤陽子。.(n)</desc>
  </programme>
  <programme start="20230317002500 +0000" stop="20230317005500 +0000" channel="フジテレビ">
    <title lang="ja">発見★街頭インタビュー!&lt;水曜RISE!&gt;【#4最終回!だから人生は面白いSP】</title>
    <desc lang="ja">街角にはナイスな出会いスゴイ発見ミラクルが!甲子園球児の息子を持つ夫婦との出会い。母と息子の絆、感動の愛の物語に。だから人生は面白い!(n)</desc>
  </programme>
  <programme start="20230317002500 +0000" stop="20230317005500 +0000" channel="フジテレビ">
    <title lang="ja">発見★街頭インタビュー!&lt;水曜RISE!&gt;【#4最終回!だから人生は面白いSP】</title>
    <desc lang="ja">街角にはナイスな出会いスゴイ発見ミラクルが!甲子園球児の息子を持つ夫婦との出会い。母と息子の絆、感動の愛の物語に。だから人生は面白い!(n)</desc>
  </programme>
  <programme start="20230317005500 +0000" stop="20230317012500 +0000" channel="フジテレビ">
    <title lang="ja">大雪海のカイナ&lt;+Ultra&gt;　#10</title>
    <desc lang="ja">建設者.(n)</desc>
  </programme>
  <programme start="20230317005500 +0000" stop="20230317012500 +0000" channel="フジテレビ">
    <title lang="ja">大雪海のカイナ&lt;+Ultra&gt;　#10</title>
    <desc lang="ja">建設者.(n)</desc>
  </programme>
  <programme start="20230317012500 +0000" stop="20230317022500 +0000" channel="フジテレビ">
    <title lang="ja">忍者に結婚は難しい&lt;Wナイト&gt;　#10[再][字][解]</title>
    <desc lang="ja">悟郎の解放を条件に、小夜から伊賀の暗殺任務を依頼された蛍。悟郎は蛍を止めるために宇良とともに脱走を図る。任務のため三姉妹の侵入大作戦がついに始動する!(n)</desc>
  </programme>
  <programme start="20230317012500 +0000" stop="20230317022500 +0000" channel="フジテレビ">
    <title lang="ja">忍者に結婚は難しい&lt;Wナイト&gt;　#10[再][字][解]</title>
    <desc lang="ja">悟郎の解放を条件に、小夜から伊賀の暗殺任務を依頼された蛍。悟郎は蛍を止めるために宇良とともに脱走を図る。任務のため三姉妹の侵入大作戦がついに始動する!(n)</desc>
  </programme>
  <programme start="20230317022500 +0000" stop="20230317032500 +0000" channel="フジテレビ">
    <title lang="ja">KANDYTOWN　LIFE&lt;Wナイト&gt;</title>
    <desc lang="ja">KANDYTOWN。人気絶頂のHIPHOPクルーが何故今終演を迎えるのか。公の場で語られなかった彼らの考え・日々に関係者の証言とともに迫った1時間。.(n)</desc>
  </programme>
  <programme start="20230317022500 +0000" stop="20230317032500 +0000" channel="フジテレビ">
    <title lang="ja">KANDYTOWN　LIFE&lt;Wナイト&gt;</title>
    <desc lang="ja">KANDYTOWN。人気絶頂のHIPHOPクルーが何故今終演を迎えるのか。公の場で語られなかった彼らの考え・日々に関係者の証言とともに迫った1時間。.(n)</desc>
  </programme>
  <programme start="20230317032500 +0000" stop="20230317035500 +0000" channel="フジテレビ">
    <title lang="ja">ディノスTHEストア</title>
    <desc lang="ja">通販のディノスが自信を持ってお届けする「今がカイドキ!」な商品をご紹介!ゲストの皆さんの本音のリアクションも交えて、商品の魅力を解説します!(n)</desc>
  </programme>
  <programme start="20230317032500 +0000" stop="20230317035500 +0000" channel="フジテレビ">
    <title lang="ja">ディノスTHEストア</title>
    <desc lang="ja">通販のディノスが自信を持ってお届けする「今がカイドキ!」な商品をご紹介!ゲストの皆さんの本音のリアクションも交えて、商品の魅力を解説します!(n)</desc>
  </programme>
  <programme start="20230317035500 +0000" stop="20230317042500 +0000" channel="フジテレビ">
    <title lang="ja">ディノスTHEストア</title>
    <desc lang="ja">通販のディノスが自信を持ってお届けする「今がカイドキ!」な商品をご紹介!ゲストの皆さんの本音のリアクションも交えて、商品の魅力を解説します!(n)</desc>
  </programme>
  <programme start="20230317035500 +0000" stop="20230317042500 +0000" channel="フジテレビ">
    <title lang="ja">ディノスTHEストア</title>
    <desc lang="ja">通販のディノスが自信を持ってお届けする「今がカイドキ!」な商品をご紹介!ゲストの皆さんの本音のリアクションも交えて、商品の魅力を解説します!(n)</desc>
  </programme>
  <programme start="20230317042500 +0000" stop="20230317045500 +0000" channel="フジテレビ">
    <title lang="ja">ディノスTHEストア</title>
    <desc lang="ja">通販のディノスが自信を持ってお届けする「今がカイドキ!」な商品をご紹介!ゲストの皆さんの本音のリアクションも交えて、商品の魅力を解説します!(n)</desc>
  </programme>
  <programme start="20230317042500 +0000" stop="20230317045500 +0000" channel="フジテレビ">
    <title lang="ja">ディノスTHEストア</title>
    <desc lang="ja">通販のディノスが自信を持ってお届けする「今がカイドキ!」な商品をご紹介!ゲストの皆さんの本音のリアクションも交えて、商品の魅力を解説します!(n)</desc>
  </programme>
  <programme start="20230317045500 +0000" stop="20230317052500 +0000" channel="フジテレビ">
    <title lang="ja">めざましテレビ全部見せ[デ]</title>
    <desc lang="ja">きょうのめざましテレビで注目しているとっておきのニュース&amp;スポーツ&amp;エンタメが全部わかります!▽更新されたばかりの最新お天気情報をチェック▽占い.(n)</desc>
  </programme>
  <programme start="20230317052500 +0000" stop="20230317080000 +0000" channel="フジテレビ">
    <title lang="ja">めざましテレビ[デ]</title>
    <desc lang="ja">ニュース&amp;スポーツにエンタメ&amp;トレンド家族で見たい新情報のシャワー▽ココ調で身近な疑問検証▽めざましじゃんけん▽きょうのわんこ▽紙兎ロペ▽占い.(n)</desc>
  </programme>
  <programme start="20230317080000 +0000" stop="20230317095000 +0000" channel="フジテレビ">
    <title lang="ja">めざまし8[字][デ]</title>
    <desc lang="ja">谷原章介&amp;永島優美と新しい朝を始めよう!目が覚める今日一番のニュースをしっかり伝えます!当事者たちを独自取材。わかるまで解説します。天達が天気を深掘り!(n)</desc>
  </programme>
  <programme start="20230317095000 +0000" stop="20230317112500 +0000" channel="フジテレビ">
    <title lang="ja">ノンストップ![字][デ]</title>
    <desc lang="ja">MCバナナマン設楽統▽今役立つ生活情報&amp;バズな話題&amp;気になるあの人&amp;旬なエンタメ情報を独自な目線で!▽本音トーク!せきららスタジオ.(n)</desc>
  </programme>
  <programme start="20230317112500 +0000" stop="20230317113000 +0000" channel="フジテレビ">
    <title lang="ja">国分太一の気ままにさんぽ[字][解]</title>
    <desc lang="ja">おさんぽ歴10年目に突入した国分太一。もはや「さんぽの達人」の域まで達したこの男が、五感を使った新たな独自の目線で日本全国を気ままにおさんぽします!!(n)</desc>
  </programme>
  <programme start="20230317113000 +0000" stop="20230317114500 +0000" channel="フジテレビ">
    <title lang="ja">FNN　Live　News　days[字]</title>
    <desc lang="ja">世の中の動きを素早くキャッチ!最新ニュースをわかりやすく、丁寧にお届けします。気になるポイントは深掘りして、役に立つニュースをお伝えします。.(n)</desc>
  </programme>
  <programme start="20230317114500 +0000" stop="20230317144500 +0000" channel="フジテレビ">
    <title lang="ja">ぽかぽか[字]</title>
    <desc lang="ja">ハライチ&amp;神田愛花がお送りするお昼の新バラエティ!豪華ゲストとのトーク企画にスタジオショー!さらには笑えるVTRコーナーも!?“ぽかぽか"なお昼を是非.(n)</desc>
  </programme>
  <programme start="20230317144500 +0000" stop="20230317154500 +0000" channel="フジテレビ">
    <title lang="ja">ライアーゲーム　シーズン2　#09[再][字][デ]</title>
    <desc lang="ja">ライアーゲームついに最終回!秋山対葛城、人生を賭けたゴールドラッシュゲーム決着!そしてナオ、最終回にして衝撃の結末!お楽しみに…戸田恵梨香　松田翔太　菊地凛子.(n)</desc>
  </programme>
  <programme start="20230317154500 +0000" stop="20230317190000 +0000" channel="フジテレビ">
    <title lang="ja">イット![字][デ]</title>
    <desc lang="ja">ソレ知りたいを速報!榎並大二郎&amp;宮司愛海が現場と生の声を取材。わかりやすく伝えます▽ガチャピンとあしたの空を先読み!▽人気企画「しらべてみたら」.(n)</desc>
  </programme>
  <programme start="20230317190000 +0000" stop="20230317200000 +0000" channel="フジテレビ">
    <title lang="ja">VS魂【岸Dがハイカロリー背徳グルメを爆食!池松壮亮&amp;浜辺美波と白熱キック】[字][デ]</title>
    <desc lang="ja">岸Dが超ハイカロリー背徳グルメを爆食!肉ドレス海鮮丼・鰻牛丼…衝撃料理が続々!池松壮亮&amp;浜辺美波の背徳グルメとは▽白熱キック対決で魂チーム仲間割れ!?(n)</desc>
  </programme>
  <programme start="20230317200000 +0000" stop="20230317210000 +0000" channel="フジテレビ">
    <title lang="ja">奇跡体験!アンビリバボー【全米震撼!人気保育園に潜む悪魔!?】[字]</title>
    <desc lang="ja">全米震撼!人気保育園に悪魔!?300人以上の園児から被害証言!不気味な儀式…地下トンネル…謎が謎を呼ぶ法廷劇!▽目が見えない女子大生に起きた愛の奇跡!(n)</desc>
  </programme>
  <programme start="20230317210000 +0000" stop="20230317215400 +0000" channel="フジテレビ">
    <title lang="ja">千鳥のクセがスゴいネタGP【TV初披露ネタ祭り!片平なぎさもギャグを初披露!?】[字]</title>
    <desc lang="ja">実力派芸人が続々登場!!爆笑ネタ連発に大御所!片平なぎさも立ち上がってギャグ熱演!!19歳の藤原大祐は思わず赤面?▽歌謡祭で大悟感動?全年代対応ギャグ完成.(n)</desc>
  </programme>
  <programme start="20230317215400 +0000" stop="20230317220000 +0000" channel="フジテレビ">
    <title lang="ja">美食ファンファーレ[字]</title>
    <desc lang="ja">グルメドラマ.(n)</desc>
  </programme>
  <programme start="20230317220000 +0000" stop="20230317225400 +0000" channel="フジテレビ">
    <title lang="ja">[終]&lt;木曜劇場&gt;忍者に結婚は難しい【最終決戦!忍者夫婦の愛の行方は】　#11[字][解][デ]</title>
    <desc lang="ja">真犯人を探していた矢先、小夜が放った手裏剣から蛍を庇い悟郎が倒れる。蛍は悟郎を連れて逃げるが、夫婦の未来のため宿敵・風富城水と対戦することを決意し・・.(n)</desc>
  </programme>
  <programme start="20230317225400 +0000" stop="20230317230000 +0000" channel="フジテレビ">
    <title lang="ja">空旅をあなたへ-PREMIUM　SKY-[字]</title>
    <desc lang="ja">旅先の「食」「遊」「楽」などの情報を紹介し、じっくりと味わいつくす上質な旅番組。毎回とっておきの現地情報を旅人であるアーティストの歌と共に紹介します。.(n)</desc>
  </programme>
  <programme start="20230317230000 +0000" stop="20230317234000 +0000" channel="フジテレビ">
    <title lang="ja">トークィーンズ【SnowMan目黒蓮登場!『silent』裏側を若槻が取材!】[字]</title>
    <desc lang="ja">Snow　Man目黒蓮が登場!一度別れた人ともう一度付き合うのはナシ?『silent』名場面とともに指原あさこ若槻みちょぱらが目黒の恋愛観を徹底取材!(n)</desc>
  </programme>
  <programme start="20230317045500 +0000" stop="20230317234000 +0000" channel="フジテレビ">
    <title lang="ja">めざましテレビ全部見せ[デ]</title>
    <desc lang="ja">きょうのめざましテレビで注目しているとっておきのニュース&amp;スポーツ&amp;エンタメが全部わかります!▽更新されたばかりの最新お天気情報をチェック▽占い.(n)</desc>
  </programme>
  <programme start="20230317234000 +0000" stop="20230318002500 +0000" channel="フジテレビ">
    <title lang="ja">FNN　Live　News　α[字]</title>
    <desc lang="ja">働く人に役立つ情報を+αして、その日のニュースをコンパクトにお伝えします。キャスターは月〜水曜日が内田嶺衣奈、木〜金曜日は小澤陽子。.(n)</desc>
  </programme>
  <programme start="20230317234000 +0000" stop="20230318002500 +0000" channel="フジテレビ">
    <title lang="ja">FNN　Live　News　α[字]</title>
    <desc lang="ja">働く人に役立つ情報を+αして、その日のニュースをコンパクトにお伝えします。キャスターは月〜水曜日が内田嶺衣奈、木〜金曜日は小澤陽子。.(n)</desc>
  </programme>
  <programme start="20230318002500 +0000" stop="20230318005500 +0000" channel="フジテレビ">
    <title lang="ja">キスマイ超BUSAIKU!?</title>
    <desc lang="ja">ジャニーズ禁断…過激テーマにキスマイが挑戦!一般女性がメッタ斬り…ブサイクの上の超ブサイクは?▽新企画!キスマイがコントに挑む…「令和のブサイクな恋」.(n)</desc>
  </programme>
  <programme start="20230318002500 +0000" stop="20230318005500 +0000" channel="フジテレビ">
    <title lang="ja">キスマイ超BUSAIKU!?</title>
    <desc lang="ja">ジャニーズ禁断…過激テーマにキスマイが挑戦!一般女性がメッタ斬り…ブサイクの上の超ブサイクは?▽新企画!キスマイがコントに挑む…「令和のブサイクな恋」.(n)</desc>
  </programme>
  <programme start="20230318005500 +0000" stop="20230318012500 +0000" channel="フジテレビ">
    <title lang="ja">うる星やつら&lt;ノイタミナ&gt;　#22[字]</title>
    <desc lang="ja">大ビン小ビン/愛がふれあうとき.(n)</desc>
  </programme>
  <programme start="20230318005500 +0000" stop="20230318012500 +0000" channel="フジテレビ">
    <title lang="ja">うる星やつら&lt;ノイタミナ&gt;　#22[字]</title>
    <desc lang="ja">大ビン小ビン/愛がふれあうとき.(n)</desc>
  </programme>
  <programme start="20230318012500 +0000" stop="20230318022500 +0000" channel="フジテレビ">
    <title lang="ja">EXITV〜FODの新作・名作をPon!Pon!見せまくり!!〜&lt;フジテレビか…</title>
    <desc lang="ja">EXIT単独MC“日本一チャラい番組!?"▽りんたろー。&amp;兼近が名作の魅力をテンションMAXで語り合う!▽ゲストの好きな作品やプライベート秘話をお届け.(n)</desc>
  </programme>
  <programme start="20230318012500 +0000" stop="20230318022500 +0000" channel="フジテレビ">
    <title lang="ja">EXITV〜FODの新作・名作をPon!Pon!見せまくり!!〜&lt;フジテレビか…</title>
    <desc lang="ja">EXIT単独MC“日本一チャラい番組!?"▽りんたろー。&amp;兼近が名作の魅力をテンションMAXで語り合う!▽ゲストの好きな作品やプライベート秘話をお届け.(n)</desc>
  </programme>
  <programme start="20230318022500 +0000" stop="20230318025500 +0000" channel="フジテレビ">
    <title lang="ja">いいすぽ!&lt;フジテレビからの!&gt;</title>
    <desc lang="ja">今話題のeSports専門番組!EVOJAPAN目前!元祖格闘ゲーム!『バーチャファイター』最強トーナメント!　MC:バカリズム.(n)</desc>
  </programme>
  <programme start="20230318022500 +0000" stop="20230318025500 +0000" channel="フジテレビ">
    <title lang="ja">いいすぽ!&lt;フジテレビからの!&gt;</title>
    <desc lang="ja">今話題のeSports専門番組!EVOJAPAN目前!元祖格闘ゲーム!『バーチャファイター』最強トーナメント!　MC:バカリズム.(n)</desc>
  </programme>
  <programme start="20230318025500 +0000" stop="20230318032500 +0000" channel="フジテレビ">
    <title lang="ja">Tune&lt;フジテレビからの!&gt;</title>
    <desc lang="ja">日本や世界の音楽シーンを代表するアーティストから、次世代を担うネクストブレイクアーティストまで、旬な情報をお届けする音楽番組です。.(n)</desc>
  </programme>
  <programme start="20230318025500 +0000" stop="20230318032500 +0000" channel="フジテレビ">
    <title lang="ja">Tune&lt;フジテレビからの!&gt;</title>
    <desc lang="ja">日本や世界の音楽シーンを代表するアーティストから、次世代を担うネクストブレイクアーティストまで、旬な情報をお届けする音楽番組です。.(n)</desc>
  </programme>
  <programme start="20230318032500 +0000" stop="20230318035500 +0000" channel="フジテレビ">
    <title lang="ja">ディノスTHEストア</title>
    <desc lang="ja">通販のディノスが自信を持ってお届けする「今がカイドキ!」な商品をご紹介!ゲストの皆さんの本音のリアクションも交えて、商品の魅力を解説します!(n)</desc>
  </programme>
  <programme start="20230318032500 +0000" stop="20230318035500 +0000" channel="フジテレビ">
    <title lang="ja">ディノスTHEストア</title>
    <desc lang="ja">通販のディノスが自信を持ってお届けする「今がカイドキ!」な商品をご紹介!ゲストの皆さんの本音のリアクションも交えて、商品の魅力を解説します!(n)</desc>
  </programme>
  <programme start="20230318035500 +0000" stop="20230318041000 +0000" channel="フジテレビ">
    <title lang="ja">ディノスTHEストア</title>
    <desc lang="ja">通販のディノスが自信を持ってお届けする「今がカイドキ!」な商品をご紹介!ゲストの皆さんの本音のリアクションも交えて、商品の魅力を解説します!(n)</desc>
  </programme>
  <programme start="20230318035500 +0000" stop="20230318041000 +0000" channel="フジテレビ">
    <title lang="ja">ディノスTHEストア</title>
    <desc lang="ja">通販のディノスが自信を持ってお届けする「今がカイドキ!」な商品をご紹介!ゲストの皆さんの本音のリアクションも交えて、商品の魅力を解説します!(n)</desc>
  </programme>
  <programme start="20230318041000 +0000" stop="20230318042000 +0000" channel="フジテレビ">
    <title lang="ja">ディノスTHEストア</title>
    <desc lang="ja">通販のディノスが自信を持ってお届けする「今がカイドキ!」な商品をご紹介!ゲストの皆さんの本音のリアクションも交えて、商品の魅力を解説します!(n)</desc>
  </programme>
  <programme start="20230318041000 +0000" stop="20230318042000 +0000" channel="フジテレビ">
    <title lang="ja">ディノスTHEストア</title>
    <desc lang="ja">通販のディノスが自信を持ってお届けする「今がカイドキ!」な商品をご紹介!ゲストの皆さんの本音のリアクションも交えて、商品の魅力を解説します!(n)</desc>
  </programme>
  <programme start="20230318042000 +0000" stop="20230318042500 +0000" channel="フジテレビ">
    <title lang="ja">SOUND　WEATHER</title>
    <desc lang="ja">メジャー、インディーズを問わず、良質なポップミュージックのプロモーションビデオにのせて、翌日のお天気をお届けする音楽プログラム。.(n)</desc>
  </programme>
  <programme start="20230318042000 +0000" stop="20230318042500 +0000" channel="フジテレビ">
    <title lang="ja">SOUND　WEATHER</title>
    <desc lang="ja">メジャー、インディーズを問わず、良質なポップミュージックのプロモーションビデオにのせて、翌日のお天気をお届けする音楽プログラム。.(n)</desc>
  </programme>
  <programme start="20230318042500 +0000" stop="20230318045500 +0000" channel="フジテレビ">
    <title lang="ja">ディノスTHEストア</title>
    <desc lang="ja">通販のディノスが自信を持ってお届けする「今がカイドキ!」な商品をご紹介!ゲストの皆さんの本音のリアクションも交えて、商品の魅力を解説します!(n)</desc>
  </programme>
  <programme start="20230318042500 +0000" stop="20230318045500 +0000" channel="フジテレビ">
    <title lang="ja">ディノスTHEストア</title>
    <desc lang="ja">通販のディノスが自信を持ってお届けする「今がカイドキ!」な商品をご紹介!ゲストの皆さんの本音のリアクションも交えて、商品の魅力を解説します!(n)</desc>
  </programme>
  <programme start="20230318045500 +0000" stop="20230318052500 +0000" channel="フジテレビ">
    <title lang="ja">めざましテレビ全部見せ[デ]</title>
    <desc lang="ja">きょうのめざましテレビで注目しているとっておきのニュース&amp;スポーツ&amp;エンタメが全部わかります!▽更新されたばかりの最新お天気情報をチェック▽占い.(n)</desc>
  </programme>
  <programme start="20230318052500 +0000" stop="20230318080000 +0000" channel="フジテレビ">
    <title lang="ja">めざましテレビ[デ]</title>
    <desc lang="ja">ニュース&amp;スポーツにエンタメ&amp;トレンド家族で見たい新情報のシャワー▽ココ調で身近な疑問検証▽めざましじゃんけん▽きょうのわんこ▽紙兎ロペ▽占い.(n)</desc>
  </programme>
  <programme start="20230318080000 +0000" stop="20230318095000 +0000" channel="フジテレビ">
    <title lang="ja">めざまし8[デ]</title>
    <desc lang="ja">谷原章介&amp;永島優美と新しい朝を始めよう!目が覚める今日一番のニュースをしっかり伝えます!当事者たちを独自取材。わかるまで解説します。天達が天気を深掘り!(n)</desc>
  </programme>
  <programme start="20230318095000 +0000" stop="20230318112500 +0000" channel="フジテレビ">
    <title lang="ja">ノンストップ![字][デ]</title>
    <desc lang="ja">MCバナナマン設楽統▽今役立つ生活情報&amp;バズな話題&amp;気になるあの人&amp;旬なエンタメ情報を独自な目線で!▽本音トーク!せきららスタジオ.(n)</desc>
  </programme>
  <programme start="20230318112500 +0000" stop="20230318113000 +0000" channel="フジテレビ">
    <title lang="ja">国分太一の気ままにさんぽ[字][解]</title>
    <desc lang="ja">おさんぽ歴10年目に突入した国分太一。もはや「さんぽの達人」の域まで達したこの男が、五感を使った新たな独自の目線で日本全国を気ままにおさんぽします!!(n)</desc>
  </programme>
  <programme start="20230318113000 +0000" stop="20230318114500 +0000" channel="フジテレビ">
    <title lang="ja">FNN　Live　News　days[字]</title>
    <desc lang="ja">世の中の動きを素早くキャッチ!最新ニュースをわかりやすく、丁寧にお届けします。気になるポイントは深掘りして、役に立つニュースをお伝えします。.(n)</desc>
  </programme>
  <programme start="20230318114500 +0000" stop="20230318144500 +0000" channel="フジテレビ">
    <title lang="ja">ぽかぽか[字]</title>
    <desc lang="ja">ハライチ&amp;神田愛花がお送りするお昼の新バラエティ!豪華ゲストとのトーク企画にスタジオショー!さらには笑えるVTRコーナーも!?“ぽかぽか"なお昼を是非.(n)</desc>
  </programme>
  <programme start="20230318144500 +0000" stop="20230318154500 +0000" channel="フジテレビ">
    <title lang="ja">メディアミックスα</title>
    <desc lang="ja">名作ドラマの再放送をはじめ、地上波、BS、CS、配信の4つのメディアと連動した新たなコンテンツも続々お届け予定!ぜひ今後のラインナップにご注目を!(n)</desc>
  </programme>
  <programme start="20230318154500 +0000" stop="20230318190000 +0000" channel="フジテレビ">
    <title lang="ja">イット![字][デ]</title>
    <desc lang="ja">ソレ知りたいを速報!榎並大二郎&amp;宮司愛海が現場と生の声を取材。わかりやすく伝えます▽ガチャピンとあしたの空を先読み!▽人気企画「しらべてみたら」.(n)</desc>
  </programme>
  <programme start="20230318190000 +0000" stop="20230318200000 +0000" channel="フジテレビ">
    <title lang="ja">坂上どうぶつ王国【全国スターどうぶつ甲子園!動物に青春を捧げる高校生が大集結】[字]</title>
    <desc lang="ja">700キロの巨体に魅せられた闘牛女子!▽〇〇を愛しすぎて自転車で60キロ爆走?▽貴重な動物が至る所にいる高校!▽震災を経て…奇跡の命を繋ぐ4人の部活動.(n)</desc>
  </programme>
  <programme start="20230318200000 +0000" stop="20230318215200 +0000" channel="フジテレビ">
    <title lang="ja">山村美紗サスペンス赤い霊柩車39FINAL〜弔の京人形〜[字][解]</title>
    <desc lang="ja">放送開始30周年記念▽石原葬儀社廃業の危機!?京友禅と京人形に秘められた30年越しの想いとは?!そして明子と婚約者・春彦に史上最悪の事件がふりかかる!(n)</desc>
  </programme>
  <programme start="20230318215200 +0000" stop="20230318215800 +0000" channel="フジテレビ">
    <title lang="ja">まもなく　人志松本の酒のツマミになる話[字]</title>
    <desc lang="ja">俳優やアスリート、文化人など様々なジャンルの豪華ゲストたちがお酒を飲みながら普段言えない悩みや疑問など「酒のツマミになる話」を本音でぶっちゃけまくる!(n)</desc>
  </programme>
  <programme start="20230318215800 +0000" stop="20230318225200 +0000" channel="フジテレビ">
    <title lang="ja">人志松本の酒のツマミになる話[字]</title>
    <desc lang="ja">俳優やアスリート、文化人など様々なジャンルの豪華ゲストたちがお酒を飲みながら普段言えない悩みや疑問など「酒のツマミになる話」を本音でぶっちゃけまくる!(n)</desc>
  </programme>
  <programme start="20230318225200 +0000" stop="20230318230000 +0000" channel="フジテレビ">
    <title lang="ja">週末はウマでしょ![字]</title>
    <desc lang="ja">競馬を愛してやまない林修先生がG1レースをはじめ注目のレースを徹底解説。豊富な経験をもとに独自の目線と鋭い切り口で熱く語り尽す競馬情報番組です!(n)</desc>
  </programme>
  <programme start="20230318230000 +0000" stop="20230318234000 +0000" channel="フジテレビ">
    <title lang="ja">全力!脱力タイムズ【小峠英二&amp;JO1金城碧海、言わない方がいい!?の巻】[字][解]</title>
    <desc lang="ja">感謝を伝える大切さを実感する!!バイきんぐ小峠英二が後輩からの言葉に感動!JO1金城碧海の言葉はまさかの拒否!?▽牡蠣美食実況▽コンプラ委員会で小峠叫ぶ!?(n)</desc>
  </programme>
  <programme start="20230318045500 +0000" stop="20230318234000 +0000" channel="フジテレビ">
    <title lang="ja">めざましテレビ全部見せ[デ]</title>
    <desc lang="ja">きょうのめざましテレビで注目しているとっておきのニュース&amp;スポーツ&amp;エンタメが全部わかります!▽更新されたばかりの最新お天気情報をチェック▽占い.(n)</desc>
  </programme>
  <programme start="20230318234000 +0000" stop="20230319001000 +0000" channel="フジテレビ">
    <title lang="ja">ネタパレ[字]</title>
    <desc lang="ja">ななまがり・レインボー▽次長課長・河本×レギュラー松本×チャンス大城コラボ▽ぴろしき5週連続勝ち抜きで賞金30万獲得なるか?VSオーサカクレオパトラ・cacao.(n)</desc>
  </programme>
</tv>